{
"meta":{"test_sets":[],"test_metrics":[],"learn_metrics":[{"best_value":"Min","name":"RMSE"}],"launch_mode":"Train","parameters":"","iteration_count":1000,"learn_sets":["learn"],"name":"experiment"},
"iterations":[
{"learn":[14.61268541],"iteration":0,"passed_time":0.1319359652,"remaining_time":131.8040292},
{"learn":[14.23196558],"iteration":1,"passed_time":0.1334163189,"remaining_time":66.57474312},
{"learn":[13.86674177],"iteration":2,"passed_time":0.1348384682,"remaining_time":44.81131758},
{"learn":[13.49946468],"iteration":3,"passed_time":0.1362830528,"remaining_time":33.93448015},
{"learn":[13.16661202],"iteration":4,"passed_time":0.1377994256,"remaining_time":27.42208569},
{"learn":[12.85632158],"iteration":5,"passed_time":0.1392882199,"remaining_time":23.0754151},
{"learn":[12.56784336],"iteration":6,"passed_time":0.1407721416,"remaining_time":19.9695338},
{"learn":[12.31617801],"iteration":7,"passed_time":0.1423942367,"remaining_time":17.65688535},
{"learn":[12.01509946],"iteration":8,"passed_time":0.1438199646,"remaining_time":15.8361761},
{"learn":[11.71512571],"iteration":9,"passed_time":0.145199749,"remaining_time":14.37477515},
{"learn":[11.43264457],"iteration":10,"passed_time":0.1466530249,"remaining_time":13.18544015},
{"learn":[11.17973129],"iteration":11,"passed_time":0.1480480466,"remaining_time":12.18928917},
{"learn":[10.93746433],"iteration":12,"passed_time":0.1494754589,"remaining_time":11.34863676},
{"learn":[10.69387075],"iteration":13,"passed_time":0.1508005069,"remaining_time":10.62066427},
{"learn":[10.4615922],"iteration":14,"passed_time":0.15235337,"remaining_time":10.00453796},
{"learn":[10.2299235],"iteration":15,"passed_time":0.1536882621,"remaining_time":9.451828119},
{"learn":[10.01419731],"iteration":16,"passed_time":0.1551664103,"remaining_time":8.972269492},
{"learn":[9.795856918],"iteration":17,"passed_time":0.1565502035,"remaining_time":8.540683326},
{"learn":[9.60040151],"iteration":18,"passed_time":0.1578717729,"remaining_time":8.151168907},
{"learn":[9.418664989],"iteration":19,"passed_time":0.15924076,"remaining_time":7.802797238},
{"learn":[9.249278645],"iteration":20,"passed_time":0.1606974948,"remaining_time":7.491564161},
{"learn":[9.090113396],"iteration":21,"passed_time":0.1622309299,"remaining_time":7.211902247},
{"learn":[8.909548708],"iteration":22,"passed_time":0.1636099965,"remaining_time":6.949868112},
{"learn":[8.740140208],"iteration":23,"passed_time":0.1650753126,"remaining_time":6.713062712},
{"learn":[8.59377682],"iteration":24,"passed_time":0.166503101,"remaining_time":6.493620939},
{"learn":[8.453885414],"iteration":25,"passed_time":0.1688357888,"remaining_time":6.324848396},
{"learn":[8.317732234],"iteration":26,"passed_time":0.1703646277,"remaining_time":6.139436397},
{"learn":[8.180896085],"iteration":27,"passed_time":0.1717895034,"remaining_time":5.963549904},
{"learn":[8.053220863],"iteration":28,"passed_time":0.173043465,"remaining_time":5.793972571},
{"learn":[7.924234474],"iteration":29,"passed_time":0.1743610546,"remaining_time":5.637674097},
{"learn":[7.818879511],"iteration":30,"passed_time":0.1757611789,"remaining_time":5.493954269},
{"learn":[7.719346395],"iteration":31,"passed_time":0.1770652448,"remaining_time":5.356223656},
{"learn":[7.624163594],"iteration":32,"passed_time":0.1783397675,"remaining_time":5.225895611},
{"learn":[7.524952543],"iteration":33,"passed_time":0.1795721355,"remaining_time":5.101961262},
{"learn":[7.424464745],"iteration":34,"passed_time":0.1812306355,"remaining_time":4.996787522},
{"learn":[7.327482321],"iteration":35,"passed_time":0.1825783051,"remaining_time":4.889041282},
{"learn":[7.238666841],"iteration":36,"passed_time":0.18394042,"remaining_time":4.787422282},
{"learn":[7.158842395],"iteration":37,"passed_time":0.1856013314,"remaining_time":4.698644232},
{"learn":[7.074348246],"iteration":38,"passed_time":0.1869370508,"remaining_time":4.606320661},
{"learn":[6.992269093],"iteration":39,"passed_time":0.1883620368,"remaining_time":4.520688883},
{"learn":[6.925219745],"iteration":40,"passed_time":0.1898267165,"remaining_time":4.440093197},
{"learn":[6.86013671],"iteration":41,"passed_time":0.1912916716,"remaining_time":4.363271939},
{"learn":[6.786739622],"iteration":42,"passed_time":0.1926913448,"remaining_time":4.288502721},
{"learn":[6.73057926],"iteration":43,"passed_time":0.1941079145,"remaining_time":4.217435597},
{"learn":[6.666356486],"iteration":44,"passed_time":0.1954711728,"remaining_time":4.148332667},
{"learn":[6.606182832],"iteration":45,"passed_time":0.1967820004,"remaining_time":4.081087573},
{"learn":[6.547854615],"iteration":46,"passed_time":0.1980711493,"remaining_time":4.016208624},
{"learn":[6.49240675],"iteration":47,"passed_time":0.1995059798,"remaining_time":3.956868599},
{"learn":[6.431317261],"iteration":48,"passed_time":0.2009146802,"remaining_time":3.899384916},
{"learn":[6.377586395],"iteration":49,"passed_time":0.2022631163,"remaining_time":3.842999209},
{"learn":[6.327558015],"iteration":50,"passed_time":0.2039075219,"remaining_time":3.794279182},
{"learn":[6.282040317],"iteration":51,"passed_time":0.2052105751,"remaining_time":3.741146638},
{"learn":[6.237655841],"iteration":52,"passed_time":0.2066070248,"remaining_time":3.691638726},
{"learn":[6.192792003],"iteration":53,"passed_time":0.2079352407,"remaining_time":3.642717365},
{"learn":[6.150579347],"iteration":54,"passed_time":0.2091715084,"remaining_time":3.593946826},
{"learn":[6.115693845],"iteration":55,"passed_time":0.2106784426,"remaining_time":3.551436604},
{"learn":[6.078780782],"iteration":56,"passed_time":0.2121680541,"remaining_time":3.51007851},
{"learn":[6.045146957],"iteration":57,"passed_time":0.2134752828,"remaining_time":3.467133041},
{"learn":[6.008080327],"iteration":58,"passed_time":0.2148105061,"remaining_time":3.426045529},
{"learn":[5.977575734],"iteration":59,"passed_time":0.2161686817,"remaining_time":3.386642681},
{"learn":[5.948036502],"iteration":60,"passed_time":0.217413796,"remaining_time":3.346746793},
{"learn":[5.914888282],"iteration":61,"passed_time":0.2188699797,"remaining_time":3.311290983},
{"learn":[5.884957796],"iteration":62,"passed_time":0.220276084,"remaining_time":3.276169694},
{"learn":[5.849539885],"iteration":63,"passed_time":0.2218234786,"remaining_time":3.244168375},
{"learn":[5.821387627],"iteration":64,"passed_time":0.2232691666,"remaining_time":3.211641089},
{"learn":[5.797012279],"iteration":65,"passed_time":0.2246049813,"remaining_time":3.178500796},
{"learn":[5.768685095],"iteration":66,"passed_time":0.2261131137,"remaining_time":3.148709478},
{"learn":[5.755484587],"iteration":67,"passed_time":0.2269048984,"remaining_time":3.109931843},
{"learn":[5.731887055],"iteration":68,"passed_time":0.2283829862,"remaining_time":3.081515365},
{"learn":[5.707148487],"iteration":69,"passed_time":0.2298703215,"remaining_time":3.053991414},
{"learn":[5.685365039],"iteration":70,"passed_time":0.2312825009,"remaining_time":3.026217511},
{"learn":[5.663541834],"iteration":71,"passed_time":0.232858652,"remaining_time":3.001289292},
{"learn":[5.638108797],"iteration":72,"passed_time":0.2345377835,"remaining_time":2.978308566},
{"learn":[5.619204893],"iteration":73,"passed_time":0.235971852,"remaining_time":2.952836959},
{"learn":[5.598472793],"iteration":74,"passed_time":0.2372707652,"remaining_time":2.926339438},
{"learn":[5.577007075],"iteration":75,"passed_time":0.2386446195,"remaining_time":2.901416163},
{"learn":[5.562637084],"iteration":76,"passed_time":0.2401995279,"remaining_time":2.87927486},
{"learn":[5.54729991],"iteration":77,"passed_time":0.2416296661,"remaining_time":2.856186566},
{"learn":[5.530737623],"iteration":78,"passed_time":0.2431176991,"remaining_time":2.834321531},
{"learn":[5.513704873],"iteration":79,"passed_time":0.2443561924,"remaining_time":2.810096212},
{"learn":[5.501575529],"iteration":80,"passed_time":0.2455902246,"remaining_time":2.786387856},
{"learn":[5.484080734],"iteration":81,"passed_time":0.2470656056,"remaining_time":2.765929585},
{"learn":[5.472178894],"iteration":82,"passed_time":0.2485486256,"remaining_time":2.746013129},
{"learn":[5.458923342],"iteration":83,"passed_time":0.2498515688,"remaining_time":2.724571869},
{"learn":[5.451382371],"iteration":84,"passed_time":0.2508875696,"remaining_time":2.700730896},
{"learn":[5.441410748],"iteration":85,"passed_time":0.2522829421,"remaining_time":2.681239641},
{"learn":[5.434047468],"iteration":86,"passed_time":0.2533981039,"remaining_time":2.65922378},
{"learn":[5.422107497],"iteration":87,"passed_time":0.255153024,"remaining_time":2.644313158},
{"learn":[5.40731265],"iteration":88,"passed_time":0.2566173878,"remaining_time":2.626724048},
{"learn":[5.396360181],"iteration":89,"passed_time":0.2579292531,"remaining_time":2.607951337},
{"learn":[5.383793239],"iteration":90,"passed_time":0.25941908,"remaining_time":2.591340041},
{"learn":[5.369605034],"iteration":91,"passed_time":0.2607464036,"remaining_time":2.573453636},
{"learn":[5.357467333],"iteration":92,"passed_time":0.262018811,"remaining_time":2.555387759},
{"learn":[5.341109968],"iteration":93,"passed_time":0.2634943021,"remaining_time":2.539636571},
{"learn":[5.330529276],"iteration":94,"passed_time":0.264997226,"remaining_time":2.524447259},
{"learn":[5.319862075],"iteration":95,"passed_time":0.2666564181,"remaining_time":2.511014603},
{"learn":[5.313052243],"iteration":96,"passed_time":0.2680020368,"remaining_time":2.494905559},
{"learn":[5.299677207],"iteration":97,"passed_time":0.2694687418,"remaining_time":2.480212297},
{"learn":[5.287546698],"iteration":98,"passed_time":0.2707165482,"remaining_time":2.463794039},
{"learn":[5.279803754],"iteration":99,"passed_time":0.272257998,"remaining_time":2.450321982},
{"learn":[5.272254612],"iteration":100,"passed_time":0.2738459937,"remaining_time":2.437500478},
{"learn":[5.268813888],"iteration":101,"passed_time":0.2747048749,"remaining_time":2.418480173},
{"learn":[5.258113767],"iteration":102,"passed_time":0.2760539225,"remaining_time":2.404081248},
{"learn":[5.251018576],"iteration":103,"passed_time":0.2775792019,"remaining_time":2.391451586},
{"learn":[5.24171237],"iteration":104,"passed_time":0.2790491195,"remaining_time":2.378561542},
{"learn":[5.233984943],"iteration":105,"passed_time":0.2807660353,"remaining_time":2.367970147},
{"learn":[5.226240449],"iteration":106,"passed_time":0.2822923576,"remaining_time":2.355953975},
{"learn":[5.220541644],"iteration":107,"passed_time":0.2836137116,"remaining_time":2.342439174},
{"learn":[5.211712096],"iteration":108,"passed_time":0.2849152213,"remaining_time":2.328985891},
{"learn":[5.203388597],"iteration":109,"passed_time":0.2862459582,"remaining_time":2.315990026},
{"learn":[5.196026544],"iteration":110,"passed_time":0.2878200342,"remaining_time":2.305153247},
{"learn":[5.188716772],"iteration":111,"passed_time":0.2891848764,"remaining_time":2.292822949},
{"learn":[5.182163132],"iteration":112,"passed_time":0.2905686602,"remaining_time":2.280835412},
{"learn":[5.17764747],"iteration":113,"passed_time":0.2918472174,"remaining_time":2.268216093},
{"learn":[5.170548056],"iteration":114,"passed_time":0.2931861344,"remaining_time":2.256258513},
{"learn":[5.165901827],"iteration":115,"passed_time":0.2943612106,"remaining_time":2.243235432},
{"learn":[5.160333668],"iteration":116,"passed_time":0.2958832125,"remaining_time":2.233033133},
{"learn":[5.148953243],"iteration":117,"passed_time":0.2972895015,"remaining_time":2.222113053},
{"learn":[5.144729126],"iteration":118,"passed_time":0.2986116222,"remaining_time":2.210729741},
{"learn":[5.139939946],"iteration":119,"passed_time":0.3000952037,"remaining_time":2.20069816},
{"learn":[5.132898872],"iteration":120,"passed_time":0.3015354275,"remaining_time":2.190492899},
{"learn":[5.129073077],"iteration":121,"passed_time":0.303211697,"remaining_time":2.182130082},
{"learn":[5.127123916],"iteration":122,"passed_time":0.3042387656,"remaining_time":2.169247134},
{"learn":[5.121282057],"iteration":123,"passed_time":0.3057634837,"remaining_time":2.160071062},
{"learn":[5.114489821],"iteration":124,"passed_time":0.3074563243,"remaining_time":2.15219427},
{"learn":[5.107777291],"iteration":125,"passed_time":0.3089685322,"remaining_time":2.143162676},
{"learn":[5.103518754],"iteration":126,"passed_time":0.3105839453,"remaining_time":2.134958931},
{"learn":[5.101133351],"iteration":127,"passed_time":0.3115947335,"remaining_time":2.122739122},
{"learn":[5.096462705],"iteration":128,"passed_time":0.3132452392,"remaining_time":2.115012429},
{"learn":[5.08562082],"iteration":129,"passed_time":0.3148040172,"remaining_time":2.106765346},
{"learn":[5.080483682],"iteration":130,"passed_time":0.3166257377,"remaining_time":2.100364626},
{"learn":[5.07437499],"iteration":131,"passed_time":0.3180926277,"remaining_time":2.091700006},
{"learn":[5.070683732],"iteration":132,"passed_time":0.3192913121,"remaining_time":2.081395245},
{"learn":[5.06432037],"iteration":133,"passed_time":0.3207011906,"remaining_time":2.072591277},
{"learn":[5.057436484],"iteration":134,"passed_time":0.3220240933,"remaining_time":2.063339561},
{"learn":[5.053254656],"iteration":135,"passed_time":0.3233037387,"remaining_time":2.053929634},
{"learn":[5.04801663],"iteration":136,"passed_time":0.3248388228,"remaining_time":2.046247475},
{"learn":[5.045680836],"iteration":137,"passed_time":0.3262032934,"remaining_time":2.037588688},
{"learn":[5.041857933],"iteration":138,"passed_time":0.3275868469,"remaining_time":2.029153059},
{"learn":[5.035264888],"iteration":139,"passed_time":0.3290371057,"remaining_time":2.021227935},
{"learn":[5.028771948],"iteration":140,"passed_time":0.3303772111,"remaining_time":2.012723577},
{"learn":[5.024912247],"iteration":141,"passed_time":0.3321297395,"remaining_time":2.006812088},
{"learn":[5.02239068],"iteration":142,"passed_time":0.3334484421,"remaining_time":1.998358845},
{"learn":[5.017110572],"iteration":143,"passed_time":0.3350237311,"remaining_time":1.991529957},
{"learn":[5.010707886],"iteration":144,"passed_time":0.3364076352,"remaining_time":1.983645021},
{"learn":[5.004389868],"iteration":145,"passed_time":0.337604064,"remaining_time":1.974752539},
{"learn":[4.997628683],"iteration":146,"passed_time":0.3390590745,"remaining_time":1.967465242},
{"learn":[4.991497851],"iteration":147,"passed_time":0.3405045915,"remaining_time":1.960202108},
{"learn":[4.988345253],"iteration":148,"passed_time":0.3420470089,"remaining_time":1.953570501},
{"learn":[4.98460423],"iteration":149,"passed_time":0.3433694152,"remaining_time":1.94576002},
{"learn":[4.982441783],"iteration":150,"passed_time":0.34481198,"remaining_time":1.938711066},
{"learn":[4.977461771],"iteration":151,"passed_time":0.3461399653,"remaining_time":1.931096649},
{"learn":[4.973601586],"iteration":152,"passed_time":0.3475388466,"remaining_time":1.923956883},
{"learn":[4.968328804],"iteration":153,"passed_time":0.348901483,"remaining_time":1.916692562},
{"learn":[4.9640736],"iteration":154,"passed_time":0.3501559759,"remaining_time":1.908914837},
{"learn":[4.960865882],"iteration":155,"passed_time":0.3515611729,"remaining_time":1.902036089},
{"learn":[4.957014156],"iteration":156,"passed_time":0.3529253729,"remaining_time":1.895006938},
{"learn":[4.952244852],"iteration":157,"passed_time":0.3543598877,"remaining_time":1.888424212},
{"learn":[4.949695675],"iteration":158,"passed_time":0.3557959813,"remaining_time":1.881914593},
{"learn":[4.946584698],"iteration":159,"passed_time":0.3571407683,"remaining_time":1.874989033},
{"learn":[4.940192834],"iteration":160,"passed_time":0.3585028281,"remaining_time":1.868222812},
{"learn":[4.936727994],"iteration":161,"passed_time":0.359997898,"remaining_time":1.862211349},
{"learn":[4.932342063],"iteration":162,"passed_time":0.3614265629,"remaining_time":1.855914314},
{"learn":[4.925830838],"iteration":163,"passed_time":0.3628533333,"remaining_time":1.849666992},
{"learn":[4.922571773],"iteration":164,"passed_time":0.3643266392,"remaining_time":1.843713599},
{"learn":[4.918395814],"iteration":165,"passed_time":0.3656514415,"remaining_time":1.837068086},
{"learn":[4.911142452],"iteration":166,"passed_time":0.3669496775,"remaining_time":1.830353781},
{"learn":[4.908276131],"iteration":167,"passed_time":0.3682904248,"remaining_time":1.823914485},
{"learn":[4.904584645],"iteration":168,"passed_time":0.3697012609,"remaining_time":1.817880164},
{"learn":[4.89795517],"iteration":169,"passed_time":0.3711104777,"remaining_time":1.811892333},
{"learn":[4.895556491],"iteration":170,"passed_time":0.3724542422,"remaining_time":1.805640741},
{"learn":[4.890591233],"iteration":171,"passed_time":0.3737979213,"remaining_time":1.799445807},
{"learn":[4.884629277],"iteration":172,"passed_time":0.3752588015,"remaining_time":1.793867219},
{"learn":[4.880550786],"iteration":173,"passed_time":0.3765499053,"remaining_time":1.78753001},
{"learn":[4.876384842],"iteration":174,"passed_time":0.3781395949,"remaining_time":1.78265809},
{"learn":[4.872638238],"iteration":175,"passed_time":0.3797247836,"remaining_time":1.777802396},
{"learn":[4.869137118],"iteration":176,"passed_time":0.3812466549,"remaining_time":1.772689248},
{"learn":[4.863587157],"iteration":177,"passed_time":0.382692999,"remaining_time":1.76726767},
{"learn":[4.858028614],"iteration":178,"passed_time":0.3841297643,"remaining_time":1.761846572},
{"learn":[4.853838176],"iteration":179,"passed_time":0.3855715268,"remaining_time":1.756492511},
{"learn":[4.853462329],"iteration":180,"passed_time":0.386338099,"remaining_time":1.748126536},
{"learn":[4.851573196],"iteration":181,"passed_time":0.3875592844,"remaining_time":1.741887333},
{"learn":[4.848442087],"iteration":182,"passed_time":0.3888816959,"remaining_time":1.736154894},
{"learn":[4.845547104],"iteration":183,"passed_time":0.3901784984,"remaining_time":1.730356819},
{"learn":[4.839868817],"iteration":184,"passed_time":0.3917670654,"remaining_time":1.725892748},
{"learn":[4.836336958],"iteration":185,"passed_time":0.3932361205,"remaining_time":1.72093657},
{"learn":[4.831124789],"iteration":186,"passed_time":0.3946084665,"remaining_time":1.715597237},
{"learn":[4.827407333],"iteration":187,"passed_time":0.3961160374,"remaining_time":1.710884162},
{"learn":[4.824088918],"iteration":188,"passed_time":0.3975560902,"remaining_time":1.705915287},
{"learn":[4.820934539],"iteration":189,"passed_time":0.3989410272,"remaining_time":1.700748589},
{"learn":[4.816975227],"iteration":190,"passed_time":0.400202337,"remaining_time":1.695097857},
{"learn":[4.812340486],"iteration":191,"passed_time":0.4015029842,"remaining_time":1.689658392},
{"learn":[4.806402747],"iteration":192,"passed_time":0.4028642421,"remaining_time":1.68451525},
{"learn":[4.801521788],"iteration":193,"passed_time":0.404323724,"remaining_time":1.679819183},
{"learn":[4.797601172],"iteration":194,"passed_time":0.405867485,"remaining_time":1.675504233},
{"learn":[4.792694629],"iteration":195,"passed_time":0.4073949253,"remaining_time":1.671150612},
{"learn":[4.789794613],"iteration":196,"passed_time":0.4088205128,"remaining_time":1.666410517},
{"learn":[4.785367055],"iteration":197,"passed_time":0.4101993743,"remaining_time":1.661514637},
{"learn":[4.780376856],"iteration":198,"passed_time":0.4115739252,"remaining_time":1.656636754},
{"learn":[4.776691261],"iteration":199,"passed_time":0.4129841245,"remaining_time":1.651936498},
{"learn":[4.773470753],"iteration":200,"passed_time":0.4144652796,"remaining_time":1.647551037},
{"learn":[4.77207327],"iteration":201,"passed_time":0.4158212188,"remaining_time":1.642699666},
{"learn":[4.767347177],"iteration":202,"passed_time":0.4172698991,"remaining_time":1.638246845},
{"learn":[4.763983068],"iteration":203,"passed_time":0.4185830974,"remaining_time":1.633294831},
{"learn":[4.761588849],"iteration":204,"passed_time":0.4198752641,"remaining_time":1.628296756},
{"learn":[4.758558086],"iteration":205,"passed_time":0.421266165,"remaining_time":1.623715218},
{"learn":[4.753678804],"iteration":206,"passed_time":0.4225459206,"remaining_time":1.61873872},
{"learn":[4.746510889],"iteration":207,"passed_time":0.4237709808,"remaining_time":1.613589504},
{"learn":[4.744840601],"iteration":208,"passed_time":0.4250039002,"remaining_time":1.608507584},
{"learn":[4.741702222],"iteration":209,"passed_time":0.4263099313,"remaining_time":1.603737361},
{"learn":[4.739352853],"iteration":210,"passed_time":0.4276446634,"remaining_time":1.599107296},
{"learn":[4.735539287],"iteration":211,"passed_time":0.4290879448,"remaining_time":1.594911795},
{"learn":[4.730726751],"iteration":212,"passed_time":0.4305499427,"remaining_time":1.59081129},
{"learn":[4.726416092],"iteration":213,"passed_time":0.4318962732,"remaining_time":1.586310611},
{"learn":[4.721293082],"iteration":214,"passed_time":0.4332851894,"remaining_time":1.581994761},
{"learn":[4.718443695],"iteration":215,"passed_time":0.4347254734,"remaining_time":1.577892459},
{"learn":[4.711627962],"iteration":216,"passed_time":0.4362111202,"remaining_time":1.573978374},
{"learn":[4.709790764],"iteration":217,"passed_time":0.4374958081,"remaining_time":1.569365697},
{"learn":[4.706913073],"iteration":218,"passed_time":0.4388803738,"remaining_time":1.565139598},
{"learn":[4.703846389],"iteration":219,"passed_time":0.4402753948,"remaining_time":1.5609764},
{"learn":[4.701001135],"iteration":220,"passed_time":0.4416384174,"remaining_time":1.556725462},
{"learn":[4.700380864],"iteration":221,"passed_time":0.4428952565,"remaining_time":1.552128421},
{"learn":[4.695837486],"iteration":222,"passed_time":0.4441789412,"remaining_time":1.547654876},
{"learn":[4.691242996],"iteration":223,"passed_time":0.4454882308,"remaining_time":1.543298514},
{"learn":[4.690284609],"iteration":224,"passed_time":0.4467611795,"remaining_time":1.538844063},
{"learn":[4.68827119],"iteration":225,"passed_time":0.4481872883,"remaining_time":1.534942306},
{"learn":[4.686922425],"iteration":226,"passed_time":0.4496451453,"remaining_time":1.531170473},
{"learn":[4.686085874],"iteration":227,"passed_time":0.4509793366,"remaining_time":1.52700021},
{"learn":[4.683230741],"iteration":228,"passed_time":0.4522336785,"remaining_time":1.522585878},
{"learn":[4.6773487],"iteration":229,"passed_time":0.4534544478,"remaining_time":1.51808663},
{"learn":[4.671462906],"iteration":230,"passed_time":0.4547137029,"remaining_time":1.513743885},
{"learn":[4.664799601],"iteration":231,"passed_time":0.4561272101,"remaining_time":1.509938351},
{"learn":[4.660979386],"iteration":232,"passed_time":0.4577212863,"remaining_time":1.506747754},
{"learn":[4.656281279],"iteration":233,"passed_time":0.4591921455,"remaining_time":1.503167451},
{"learn":[4.651997094],"iteration":234,"passed_time":0.4606224754,"remaining_time":1.499473165},
{"learn":[4.650151977],"iteration":235,"passed_time":0.4620923428,"remaining_time":1.495926059},
{"learn":[4.648478046],"iteration":236,"passed_time":0.4637709582,"remaining_time":1.493068528},
{"learn":[4.646364602],"iteration":237,"passed_time":0.4653310494,"remaining_time":1.489841427},
{"learn":[4.642635873],"iteration":238,"passed_time":0.4668835819,"remaining_time":1.486604209},
{"learn":[4.640860821],"iteration":239,"passed_time":0.4682908786,"remaining_time":1.482921116},
{"learn":[4.639446822],"iteration":240,"passed_time":0.4696248342,"remaining_time":1.47902593},
{"learn":[4.637120072],"iteration":241,"passed_time":0.4711916822,"remaining_time":1.475881385},
{"learn":[4.633769267],"iteration":242,"passed_time":0.4728276964,"remaining_time":1.472965293},
{"learn":[4.630491517],"iteration":243,"passed_time":0.4741793605,"remaining_time":1.469178674},
{"learn":[4.627813333],"iteration":244,"passed_time":0.4756645459,"remaining_time":1.465823397},
{"learn":[4.622496304],"iteration":245,"passed_time":0.4772172588,"remaining_time":1.462690297},
{"learn":[4.618979301],"iteration":246,"passed_time":0.4785451138,"remaining_time":1.458884497},
{"learn":[4.616563458],"iteration":247,"passed_time":0.4798961965,"remaining_time":1.455169112},
{"learn":[4.614759385],"iteration":248,"passed_time":0.4812258459,"remaining_time":1.451408073},
{"learn":[4.61251363],"iteration":249,"passed_time":0.4827064448,"remaining_time":1.448119334},
{"learn":[4.608796693],"iteration":250,"passed_time":0.4840317188,"remaining_time":1.444381503},
{"learn":[4.60847774],"iteration":251,"passed_time":0.4851729206,"remaining_time":1.440116447},
{"learn":[4.605195659],"iteration":252,"passed_time":0.4863659009,"remaining_time":1.436028964},
{"learn":[4.60103766],"iteration":253,"passed_time":0.4880556184,"remaining_time":1.433423194},
{"learn":[4.599325598],"iteration":254,"passed_time":0.4896143918,"remaining_time":1.430442047},
{"learn":[4.597012808],"iteration":255,"passed_time":0.4910359092,"remaining_time":1.427073111},
{"learn":[4.594161533],"iteration":256,"passed_time":0.4926091632,"remaining_time":1.424158009},
{"learn":[4.592197259],"iteration":257,"passed_time":0.4941212954,"remaining_time":1.421077524},
{"learn":[4.58952828],"iteration":258,"passed_time":0.4957103385,"remaining_time":1.418229193},
{"learn":[4.585816572],"iteration":259,"passed_time":0.4969973668,"remaining_time":1.414530967},
{"learn":[4.582934052],"iteration":260,"passed_time":0.4983933812,"remaining_time":1.411159803},
{"learn":[4.582234842],"iteration":261,"passed_time":0.499844211,"remaining_time":1.407958121},
{"learn":[4.57571562],"iteration":262,"passed_time":0.5012394733,"remaining_time":1.404614037},
{"learn":[4.571197349],"iteration":263,"passed_time":0.5027587834,"remaining_time":1.401630548},
{"learn":[4.56723703],"iteration":264,"passed_time":0.5042574522,"remaining_time":1.398600858},
{"learn":[4.560335567],"iteration":265,"passed_time":0.5056531905,"remaining_time":1.395298653},
{"learn":[4.554709345],"iteration":266,"passed_time":0.5070127894,"remaining_time":1.391911515},
{"learn":[4.552806306],"iteration":267,"passed_time":0.508325597,"remaining_time":1.388411705},
{"learn":[4.550766241],"iteration":268,"passed_time":0.5097005288,"remaining_time":1.385096976},
{"learn":[4.549216045],"iteration":269,"passed_time":0.5111599002,"remaining_time":1.382024915},
{"learn":[4.547687452],"iteration":270,"passed_time":0.5128398483,"remaining_time":1.379558116},
{"learn":[4.545642435],"iteration":271,"passed_time":0.5143223376,"remaining_time":1.376568609},
{"learn":[4.543930359],"iteration":272,"passed_time":0.5157522002,"remaining_time":1.373449998},
{"learn":[4.541029943],"iteration":273,"passed_time":0.5170746518,"remaining_time":1.370059114},
{"learn":[4.537781449],"iteration":274,"passed_time":0.5183419611,"remaining_time":1.366537897},
{"learn":[4.53066128],"iteration":275,"passed_time":0.5195816573,"remaining_time":1.362960579},
{"learn":[4.526763956],"iteration":276,"passed_time":0.5208047724,"remaining_time":1.359356861},
{"learn":[4.522036004],"iteration":277,"passed_time":0.5221424718,"remaining_time":1.356067858},
{"learn":[4.515307629],"iteration":278,"passed_time":0.5234829481,"remaining_time":1.35280002},
{"learn":[4.51109143],"iteration":279,"passed_time":0.5250213656,"remaining_time":1.35005494},
{"learn":[4.508233494],"iteration":280,"passed_time":0.5262430772,"remaining_time":1.346508087},
{"learn":[4.502555629],"iteration":281,"passed_time":0.527519524,"remaining_time":1.343117086},
{"learn":[4.500081355],"iteration":282,"passed_time":0.5287802625,"remaining_time":1.33970123},
{"learn":[4.495281743],"iteration":283,"passed_time":0.5299838391,"remaining_time":1.336156439},
{"learn":[4.492138869],"iteration":284,"passed_time":0.5311814812,"remaining_time":1.33261319},
{"learn":[4.491708261],"iteration":285,"passed_time":0.5326161817,"remaining_time":1.32967816},
{"learn":[4.489398865],"iteration":286,"passed_time":0.5339459259,"remaining_time":1.32649284},
{"learn":[4.485796373],"iteration":287,"passed_time":0.5352695106,"remaining_time":1.323305179},
{"learn":[4.479542205],"iteration":288,"passed_time":0.5366921259,"remaining_time":1.320374054},
{"learn":[4.475986993],"iteration":289,"passed_time":0.5380122562,"remaining_time":1.31720242},
{"learn":[4.468661855],"iteration":290,"passed_time":0.5394207316,"remaining_time":1.314258758},
{"learn":[4.463785664],"iteration":291,"passed_time":0.5406418973,"remaining_time":1.31087145},
{"learn":[4.460445831],"iteration":292,"passed_time":0.5419776567,"remaining_time":1.307775438},
{"learn":[4.45692492],"iteration":293,"passed_time":0.5433379422,"remaining_time":1.304750297},
{"learn":[4.454031688],"iteration":294,"passed_time":0.5447921057,"remaining_time":1.301960795},
{"learn":[4.451672391],"iteration":295,"passed_time":0.5462931751,"remaining_time":1.299291876},
{"learn":[4.45031553],"iteration":296,"passed_time":0.5476342684,"remaining_time":1.296252157},
{"learn":[4.446782666],"iteration":297,"passed_time":0.5490376909,"remaining_time":1.293370668},
{"learn":[4.444369689],"iteration":298,"passed_time":0.5503337114,"remaining_time":1.290247263},
{"learn":[4.44411683],"iteration":299,"passed_time":0.5515951416,"remaining_time":1.28705533},
{"learn":[4.440876943],"iteration":300,"passed_time":0.5528711834,"remaining_time":1.283910157},
{"learn":[4.439336453],"iteration":301,"passed_time":0.554191384,"remaining_time":1.280879424},
{"learn":[4.436666901],"iteration":302,"passed_time":0.5555476495,"remaining_time":1.277942943},
{"learn":[4.433043336],"iteration":303,"passed_time":0.5568067894,"remaining_time":1.274794492},
{"learn":[4.431419305],"iteration":304,"passed_time":0.5581006048,"remaining_time":1.271737444},
{"learn":[4.428859646],"iteration":305,"passed_time":0.5594779477,"remaining_time":1.268881359},
{"learn":[4.424552441],"iteration":306,"passed_time":0.5608468646,"remaining_time":1.266015887},
{"learn":[4.422706391],"iteration":307,"passed_time":0.5620845607,"remaining_time":1.262865312},
{"learn":[4.421427994],"iteration":308,"passed_time":0.5634639132,"remaining_time":1.260043896},
{"learn":[4.418733158],"iteration":309,"passed_time":0.5648558876,"remaining_time":1.257259879},
{"learn":[4.415656941],"iteration":310,"passed_time":0.5662026142,"remaining_time":1.25438457},
{"learn":[4.410747417],"iteration":311,"passed_time":0.5675027608,"remaining_time":1.251416344},
{"learn":[4.408126521],"iteration":312,"passed_time":0.5688751156,"remaining_time":1.248617266},
{"learn":[4.407843853],"iteration":313,"passed_time":0.5700309042,"remaining_time":1.245354141},
{"learn":[4.405219398],"iteration":314,"passed_time":0.5714250631,"remaining_time":1.242622756},
{"learn":[4.402708465],"iteration":315,"passed_time":0.572753269,"remaining_time":1.239757076},
{"learn":[4.40104971],"iteration":316,"passed_time":0.5740043534,"remaining_time":1.236734932},
{"learn":[4.400830038],"iteration":317,"passed_time":0.5752935874,"remaining_time":1.233805744},
{"learn":[4.39784288],"iteration":318,"passed_time":0.5766413169,"remaining_time":1.231011714},
{"learn":[4.393741845],"iteration":319,"passed_time":0.5779524805,"remaining_time":1.228149021},
{"learn":[4.393425936],"iteration":320,"passed_time":0.5790754771,"remaining_time":1.224897972},
{"learn":[4.390505974],"iteration":321,"passed_time":0.5803601449,"remaining_time":1.222000554},
{"learn":[4.390305136],"iteration":322,"passed_time":0.5815329151,"remaining_time":1.218878587},
{"learn":[4.38568203],"iteration":323,"passed_time":0.5829087637,"remaining_time":1.216192359},
{"learn":[4.383057135],"iteration":324,"passed_time":0.584244288,"remaining_time":1.213430444},
{"learn":[4.380662684],"iteration":325,"passed_time":0.5857452325,"remaining_time":1.211019284},
{"learn":[4.37805727],"iteration":326,"passed_time":0.5871255978,"remaining_time":1.208365527},
{"learn":[4.373708319],"iteration":327,"passed_time":0.5885451157,"remaining_time":1.205799749},
{"learn":[4.36887921],"iteration":328,"passed_time":0.5897917091,"remaining_time":1.202888258},
{"learn":[4.367895929],"iteration":329,"passed_time":0.5910829732,"remaining_time":1.200077552},
{"learn":[4.362140573],"iteration":330,"passed_time":0.592282189,"remaining_time":1.197089983},
{"learn":[4.361931924],"iteration":331,"passed_time":0.5933620687,"remaining_time":1.193873078},
{"learn":[4.359656377],"iteration":332,"passed_time":0.5945824069,"remaining_time":1.190950346},
{"learn":[4.354281355],"iteration":333,"passed_time":0.5958129303,"remaining_time":1.188058119},
{"learn":[4.348589447],"iteration":334,"passed_time":0.5970897086,"remaining_time":1.18526763},
{"learn":[4.346355698],"iteration":335,"passed_time":0.5984285007,"remaining_time":1.182608704},
{"learn":[4.343894047],"iteration":336,"passed_time":0.5997672072,"remaining_time":1.179957443},
{"learn":[4.341561356],"iteration":337,"passed_time":0.6010551385,"remaining_time":1.177214502},
{"learn":[4.338869061],"iteration":338,"passed_time":0.602348137,"remaining_time":1.174490025},
{"learn":[4.333720063],"iteration":339,"passed_time":0.603626429,"remaining_time":1.171745421},
{"learn":[4.330892223],"iteration":340,"passed_time":0.6050249041,"remaining_time":1.169241677},
{"learn":[4.328311474],"iteration":341,"passed_time":0.6063479122,"remaining_time":1.1665992},
{"learn":[4.324580133],"iteration":342,"passed_time":0.6075886659,"remaining_time":1.163806862},
{"learn":[4.323354432],"iteration":343,"passed_time":0.6089252978,"remaining_time":1.161206382},
{"learn":[4.323159553],"iteration":344,"passed_time":0.6101894247,"remaining_time":1.158475574},
{"learn":[4.318639682],"iteration":345,"passed_time":0.6115514244,"remaining_time":1.155938241},
{"learn":[4.312712208],"iteration":346,"passed_time":0.613018144,"remaining_time":1.153604749},
{"learn":[4.311461062],"iteration":347,"passed_time":0.6143190521,"remaining_time":1.15096558},
{"learn":[4.311178356],"iteration":348,"passed_time":0.6156611324,"remaining_time":1.14841088},
{"learn":[4.311102505],"iteration":349,"passed_time":0.6168580625,"remaining_time":1.145593545},
{"learn":[4.310232308],"iteration":350,"passed_time":0.6181329709,"remaining_time":1.142929624},
{"learn":[4.305128197],"iteration":351,"passed_time":0.6195397013,"remaining_time":1.140516268},
{"learn":[4.304595496],"iteration":352,"passed_time":0.6208740479,"remaining_time":1.137975946},
{"learn":[4.3004992],"iteration":353,"passed_time":0.622185477,"remaining_time":1.135400616},
{"learn":[4.297581524],"iteration":354,"passed_time":0.6234986151,"remaining_time":1.132835512},
{"learn":[4.297355825],"iteration":355,"passed_time":0.6247527973,"remaining_time":1.130170791},
{"learn":[4.295758715],"iteration":356,"passed_time":0.6261783994,"remaining_time":1.127822719},
{"learn":[4.292500657],"iteration":357,"passed_time":0.6274668469,"remaining_time":1.125233843},
{"learn":[4.290797586],"iteration":358,"passed_time":0.6287835241,"remaining_time":1.122702616},
{"learn":[4.286410608],"iteration":359,"passed_time":0.6301754032,"remaining_time":1.120311828},
{"learn":[4.280278245],"iteration":360,"passed_time":0.6316409246,"remaining_time":1.118056927},
{"learn":[4.279941283],"iteration":361,"passed_time":0.6329921728,"remaining_time":1.11560499},
{"learn":[4.274426275],"iteration":362,"passed_time":0.634438386,"remaining_time":1.113325763},
{"learn":[4.273567658],"iteration":363,"passed_time":0.6358410971,"remaining_time":1.110975104},
{"learn":[4.269488271],"iteration":364,"passed_time":0.6372410862,"remaining_time":1.108624903},
{"learn":[4.266838205],"iteration":365,"passed_time":0.6385322802,"remaining_time":1.106091436},
{"learn":[4.263456509],"iteration":366,"passed_time":0.6399020592,"remaining_time":1.103700282},
{"learn":[4.260360204],"iteration":367,"passed_time":0.641160502,"remaining_time":1.101123471},
{"learn":[4.255120549],"iteration":368,"passed_time":0.6424731538,"remaining_time":1.098646504},
{"learn":[4.252582211],"iteration":369,"passed_time":0.6438705213,"remaining_time":1.096320077},
{"learn":[4.247857931],"iteration":370,"passed_time":0.6453110613,"remaining_time":1.094071853},
{"learn":[4.245288911],"iteration":371,"passed_time":0.6466043952,"remaining_time":1.091579463},
{"learn":[4.24048515],"iteration":372,"passed_time":0.6478790084,"remaining_time":1.089062033},
{"learn":[4.2378365],"iteration":373,"passed_time":0.6490985998,"remaining_time":1.086459154},
{"learn":[4.236751063],"iteration":374,"passed_time":0.6504693959,"remaining_time":1.08411566},
{"learn":[4.233240093],"iteration":375,"passed_time":0.6518574002,"remaining_time":1.081805898},
{"learn":[4.230358421],"iteration":376,"passed_time":0.6531780473,"remaining_time":1.079389717},
{"learn":[4.225853583],"iteration":377,"passed_time":0.6545210447,"remaining_time":1.077016111},
{"learn":[4.224702126],"iteration":378,"passed_time":0.6557742845,"remaining_time":1.074500873},
{"learn":[4.224361982],"iteration":379,"passed_time":0.6570717994,"remaining_time":1.072064515},
{"learn":[4.223787954],"iteration":380,"passed_time":0.6584447062,"remaining_time":1.069756622},
{"learn":[4.22144054],"iteration":381,"passed_time":0.6598213522,"remaining_time":1.067459675},
{"learn":[4.217739335],"iteration":382,"passed_time":0.6611227364,"remaining_time":1.065046288},
{"learn":[4.215611665],"iteration":383,"passed_time":0.6626186131,"remaining_time":1.062950692},
{"learn":[4.210236863],"iteration":384,"passed_time":0.66403381,"remaining_time":1.060729333},
{"learn":[4.208454294],"iteration":385,"passed_time":0.6652465894,"remaining_time":1.058190171},
{"learn":[4.207446501],"iteration":386,"passed_time":0.6666054362,"remaining_time":1.055889231},
{"learn":[4.204985442],"iteration":387,"passed_time":0.6679725635,"remaining_time":1.053606208},
{"learn":[4.202796622],"iteration":388,"passed_time":0.6692655115,"remaining_time":1.051211382},
{"learn":[4.199774004],"iteration":389,"passed_time":0.6705849563,"remaining_time":1.04886365},
{"learn":[4.199458358],"iteration":390,"passed_time":0.6717758611,"remaining_time":1.04632097},
{"learn":[4.19751254],"iteration":391,"passed_time":0.6733156417,"remaining_time":1.044326301},
{"learn":[4.195201346],"iteration":392,"passed_time":0.6747150348,"remaining_time":1.042117115},
{"learn":[4.190593508],"iteration":393,"passed_time":0.6760698965,"remaining_time":1.039843546},
{"learn":[4.187212054],"iteration":394,"passed_time":0.677372439,"remaining_time":1.037494495},
{"learn":[4.184984466],"iteration":395,"passed_time":0.6786012679,"remaining_time":1.035038298},
{"learn":[4.182832144],"iteration":396,"passed_time":0.6799188271,"remaining_time":1.032723055},
{"learn":[4.179752812],"iteration":397,"passed_time":0.6812927269,"remaining_time":1.030498044},
{"learn":[4.17878934],"iteration":398,"passed_time":0.6825212047,"remaining_time":1.028058256},
{"learn":[4.174548229],"iteration":399,"passed_time":0.6838475565,"remaining_time":1.025771335},
{"learn":[4.168872556],"iteration":400,"passed_time":0.6851412969,"remaining_time":1.023440491},
{"learn":[4.163926494],"iteration":401,"passed_time":0.6863897144,"remaining_time":1.021047386},
{"learn":[4.159485076],"iteration":402,"passed_time":0.687894589,"remaining_time":1.019039875},
{"learn":[4.155926102],"iteration":403,"passed_time":0.6891823746,"remaining_time":1.016714592},
{"learn":[4.153540115],"iteration":404,"passed_time":0.6906545777,"remaining_time":1.014665367},
{"learn":[4.150983044],"iteration":405,"passed_time":0.6919767987,"remaining_time":1.012399553},
{"learn":[4.146539132],"iteration":406,"passed_time":0.6933767025,"remaining_time":1.010251559},
{"learn":[4.144869174],"iteration":407,"passed_time":0.6947131136,"remaining_time":1.008015106},
{"learn":[4.142825962],"iteration":408,"passed_time":0.6961374431,"remaining_time":1.005910095},
{"learn":[4.142467378],"iteration":409,"passed_time":0.6974585313,"remaining_time":1.003659838},
{"learn":[4.141800768],"iteration":410,"passed_time":0.6986793407,"remaining_time":1.001270393},
{"learn":[4.140107084],"iteration":411,"passed_time":0.6998721506,"remaining_time":0.9988466615},
{"learn":[4.136243196],"iteration":412,"passed_time":0.7013722129,"remaining_time":0.9968655907},
{"learn":[4.133618439],"iteration":413,"passed_time":0.7028262759,"remaining_time":0.9948217335},
{"learn":[4.131053025],"iteration":414,"passed_time":0.7043986728,"remaining_time":0.9929475268},
{"learn":[4.128379975],"iteration":415,"passed_time":0.7056544635,"remaining_time":0.9906303046},
{"learn":[4.127068571],"iteration":416,"passed_time":0.7069575224,"remaining_time":0.988384258},
{"learn":[4.125969877],"iteration":417,"passed_time":0.7082049533,"remaining_time":0.9860652699},
{"learn":[4.123893633],"iteration":418,"passed_time":0.7095525272,"remaining_time":0.9838902585},
{"learn":[4.119643722],"iteration":419,"passed_time":0.710778339,"remaining_time":0.9815510396},
{"learn":[4.11465686],"iteration":420,"passed_time":0.7120566811,"remaining_time":0.9792893548},
{"learn":[4.111565986],"iteration":421,"passed_time":0.713349419,"remaining_time":0.9770520478},
{"learn":[4.106322452],"iteration":422,"passed_time":0.7146194204,"remaining_time":0.9747881929},
{"learn":[4.104222175],"iteration":423,"passed_time":0.7159006397,"remaining_time":0.9725442652},
{"learn":[4.103008002],"iteration":424,"passed_time":0.7171781497,"remaining_time":0.9702998496},
{"learn":[4.099176337],"iteration":425,"passed_time":0.7187215742,"remaining_time":0.9684182713},
{"learn":[4.096525716],"iteration":426,"passed_time":0.7199993352,"remaining_time":0.9661817776},
{"learn":[4.094967724],"iteration":427,"passed_time":0.7213947028,"remaining_time":0.9641069393},
{"learn":[4.094683584],"iteration":428,"passed_time":0.7227482917,"remaining_time":0.961979661},
{"learn":[4.091096563],"iteration":429,"passed_time":0.7240241276,"remaining_time":0.9597529133},
{"learn":[4.089178677],"iteration":430,"passed_time":0.72535719,"remaining_time":0.9576061279},
{"learn":[4.085335077],"iteration":431,"passed_time":0.7266860074,"remaining_time":0.9554575283},
{"learn":[4.084852122],"iteration":432,"passed_time":0.7279856077,"remaining_time":0.9532744563},
{"learn":[4.080322952],"iteration":433,"passed_time":0.7294612194,"remaining_time":0.9513250004},
{"learn":[4.077449519],"iteration":434,"passed_time":0.7308904107,"remaining_time":0.94931743},
{"learn":[4.076568374],"iteration":435,"passed_time":0.7321066988,"remaining_time":0.9470371058},
{"learn":[4.076071793],"iteration":436,"passed_time":0.7332899301,"remaining_time":0.9447190632},
{"learn":[4.075027644],"iteration":437,"passed_time":0.7345421623,"remaining_time":0.9424947379},
{"learn":[4.07020837],"iteration":438,"passed_time":0.7358931045,"remaining_time":0.9404009832},
{"learn":[4.06833694],"iteration":439,"passed_time":0.737182409,"remaining_time":0.9382321569},
{"learn":[4.063936568],"iteration":440,"passed_time":0.7385159481,"remaining_time":0.93612339},
{"learn":[4.061734926],"iteration":441,"passed_time":0.7397812628,"remaining_time":0.9339320014},
{"learn":[4.060815619],"iteration":442,"passed_time":0.741106747,"remaining_time":0.9318204471},
{"learn":[4.056407489],"iteration":443,"passed_time":0.7423654805,"remaining_time":0.9296288449},
{"learn":[4.05238936],"iteration":444,"passed_time":0.7435700997,"remaining_time":0.9273739445},
{"learn":[4.049685254],"iteration":445,"passed_time":0.7448880501,"remaining_time":0.9252645286},
{"learn":[4.045162016],"iteration":446,"passed_time":0.7461283378,"remaining_time":0.9230625745},
{"learn":[4.042955482],"iteration":447,"passed_time":0.7474847585,"remaining_time":0.921008006},
{"learn":[4.041467663],"iteration":448,"passed_time":0.7489856228,"remaining_time":0.9191338044},
{"learn":[4.038920476],"iteration":449,"passed_time":0.7504445281,"remaining_time":0.9172099788},
{"learn":[4.036694383],"iteration":450,"passed_time":0.7517547594,"remaining_time":0.9151072348},
{"learn":[4.034999007],"iteration":451,"passed_time":0.7529739647,"remaining_time":0.9128976387},
{"learn":[4.031928018],"iteration":452,"passed_time":0.7543442651,"remaining_time":0.9108748631},
{"learn":[4.028718143],"iteration":453,"passed_time":0.7557790654,"remaining_time":0.9089325324},
{"learn":[4.027401978],"iteration":454,"passed_time":0.7570316937,"remaining_time":0.9067742266},
{"learn":[4.025930598],"iteration":455,"passed_time":0.7583129276,"remaining_time":0.9046540189},
{"learn":[4.021074523],"iteration":456,"passed_time":0.7596370688,"remaining_time":0.9025884647},
{"learn":[4.020268486],"iteration":457,"passed_time":0.76085057,"remaining_time":0.9003952161},
{"learn":[4.017986361],"iteration":458,"passed_time":0.7619985587,"remaining_time":0.8981290202},
{"learn":[4.014814804],"iteration":459,"passed_time":0.7635222296,"remaining_time":0.8963087043},
{"learn":[4.009704796],"iteration":460,"passed_time":0.764982238,"remaining_time":0.8944152413},
{"learn":[4.008440457],"iteration":461,"passed_time":0.7662882032,"remaining_time":0.8923442712},
{"learn":[4.004854849],"iteration":462,"passed_time":0.767743334,"remaining_time":0.890449612},
{"learn":[4.000898028],"iteration":463,"passed_time":0.7691744753,"remaining_time":0.8885291352},
{"learn":[3.996617985],"iteration":464,"passed_time":0.7706499566,"remaining_time":0.886661778},
{"learn":[3.995443319],"iteration":465,"passed_time":0.7719542525,"remaining_time":0.8845999374},
{"learn":[3.990771995],"iteration":466,"passed_time":0.7733821062,"remaining_time":0.8826823611},
{"learn":[3.989249359],"iteration":467,"passed_time":0.7746512355,"remaining_time":0.8805864472},
{"learn":[3.986599538],"iteration":468,"passed_time":0.7760337358,"remaining_time":0.8786224173},
{"learn":[3.985628919],"iteration":469,"passed_time":0.7773410401,"remaining_time":0.8765760665},
{"learn":[3.985086112],"iteration":470,"passed_time":0.7786995411,"remaining_time":0.8745903551},
{"learn":[3.98466839],"iteration":471,"passed_time":0.7799851713,"remaining_time":0.8725257849},
{"learn":[3.984233894],"iteration":472,"passed_time":0.7812025221,"remaining_time":0.8703884337},
{"learn":[3.981855845],"iteration":473,"passed_time":0.7825063575,"remaining_time":0.8683509368},
{"learn":[3.978684264],"iteration":474,"passed_time":0.7839596036,"remaining_time":0.8664816672},
{"learn":[3.974361269],"iteration":475,"passed_time":0.7852903658,"remaining_time":0.8644793103},
{"learn":[3.972074049],"iteration":476,"passed_time":0.7865479364,"remaining_time":0.8623995194},
{"learn":[3.97191982],"iteration":477,"passed_time":0.787922497,"remaining_time":0.8604509277},
{"learn":[3.969616848],"iteration":478,"passed_time":0.7893378792,"remaining_time":0.8585491337},
{"learn":[3.968533527],"iteration":479,"passed_time":0.7905783674,"remaining_time":0.856459898},
{"learn":[3.967568753],"iteration":480,"passed_time":0.792094118,"remaining_time":0.8546712001},
{"learn":[3.966232553],"iteration":481,"passed_time":0.7934105899,"remaining_time":0.8526694721},
{"learn":[3.961522393],"iteration":482,"passed_time":0.7948289899,"remaining_time":0.8507796848},
{"learn":[3.955829553],"iteration":483,"passed_time":0.7966162946,"remaining_time":0.8492851406},
{"learn":[3.954248095],"iteration":484,"passed_time":0.7979697933,"remaining_time":0.8473287495},
{"learn":[3.951922606],"iteration":485,"passed_time":0.7993430059,"remaining_time":0.8453956894},
{"learn":[3.94978202],"iteration":486,"passed_time":0.8008045627,"remaining_time":0.843557989},
{"learn":[3.949518999],"iteration":487,"passed_time":0.8022545307,"remaining_time":0.8417096716},
{"learn":[3.945431216],"iteration":488,"passed_time":0.8035537446,"remaining_time":0.8397054468},
{"learn":[3.943249086],"iteration":489,"passed_time":0.8048524573,"remaining_time":0.837703578},
{"learn":[3.941981548],"iteration":490,"passed_time":0.8063185152,"remaining_time":0.8358780535},
{"learn":[3.936600517],"iteration":491,"passed_time":0.8079036787,"remaining_time":0.8341769691},
{"learn":[3.934476885],"iteration":492,"passed_time":0.8091680361,"remaining_time":0.8321464388},
{"learn":[3.93045798],"iteration":493,"passed_time":0.8104918511,"remaining_time":0.8301799122},
{"learn":[3.925977375],"iteration":494,"passed_time":0.8118172199,"remaining_time":0.8282175678},
{"learn":[3.92457993],"iteration":495,"passed_time":0.813153977,"remaining_time":0.8262693637},
{"learn":[3.919849146],"iteration":496,"passed_time":0.8144665841,"remaining_time":0.8242991787},
{"learn":[3.919681964],"iteration":497,"passed_time":0.8157474726,"remaining_time":0.8222996611},
{"learn":[3.917633027],"iteration":498,"passed_time":0.8170907458,"remaining_time":0.8203656586},
{"learn":[3.916616419],"iteration":499,"passed_time":0.8183998789,"remaining_time":0.8183998789},
{"learn":[3.912896166],"iteration":500,"passed_time":0.8195998766,"remaining_time":0.8163280208},
{"learn":[3.912769674],"iteration":501,"passed_time":0.8209626783,"remaining_time":0.814421143},
{"learn":[3.909373788],"iteration":502,"passed_time":0.822381283,"remaining_time":0.8125715659},
{"learn":[3.906706036],"iteration":503,"passed_time":0.8240028815,"remaining_time":0.8109234707},
{"learn":[3.903895664],"iteration":504,"passed_time":0.8256524502,"remaining_time":0.8093028968},
{"learn":[3.902982967],"iteration":505,"passed_time":0.8271016557,"remaining_time":0.8074865967},
{"learn":[3.900905528],"iteration":506,"passed_time":0.8286629403,"remaining_time":0.8057807289},
{"learn":[3.897463465],"iteration":507,"passed_time":0.8302079444,"remaining_time":0.8040596627},
{"learn":[3.895918033],"iteration":508,"passed_time":0.8316933503,"remaining_time":0.8022817977},
{"learn":[3.893921936],"iteration":509,"passed_time":0.8332762582,"remaining_time":0.8005987579},
{"learn":[3.890237934],"iteration":510,"passed_time":0.8346239518,"remaining_time":0.7986910224},
{"learn":[3.887311613],"iteration":511,"passed_time":0.835887668,"remaining_time":0.7967054335},
{"learn":[3.884869735],"iteration":512,"passed_time":0.8375599677,"remaining_time":0.7951105346},
{"learn":[3.882101231],"iteration":513,"passed_time":0.8390103567,"remaining_time":0.7933055124},
{"learn":[3.88060368],"iteration":514,"passed_time":0.8405283031,"remaining_time":0.7915654893},
{"learn":[3.877726076],"iteration":515,"passed_time":0.8419340113,"remaining_time":0.7897210493},
{"learn":[3.874938145],"iteration":516,"passed_time":0.8434337327,"remaining_time":0.7879661372},
{"learn":[3.874340833],"iteration":517,"passed_time":0.844747603,"remaining_time":0.7860392754},
{"learn":[3.873105224],"iteration":518,"passed_time":0.8462237961,"remaining_time":0.7842652137},
{"learn":[3.869800236],"iteration":519,"passed_time":0.8476885007,"remaining_time":0.7824816929},
{"learn":[3.867932518],"iteration":520,"passed_time":0.8494892443,"remaining_time":0.7810083455},
{"learn":[3.866666962],"iteration":521,"passed_time":0.8507747842,"remaining_time":0.7790619672},
{"learn":[3.865527652],"iteration":522,"passed_time":0.8522804204,"remaining_time":0.7773188538},
{"learn":[3.861900081],"iteration":523,"passed_time":0.8536915821,"remaining_time":0.7754908265},
{"learn":[3.858502887],"iteration":524,"passed_time":0.8551262272,"remaining_time":0.7736856341},
{"learn":[3.858335097],"iteration":525,"passed_time":0.8568482002,"remaining_time":0.7721407735},
{"learn":[3.855719306],"iteration":526,"passed_time":0.858402793,"remaining_time":0.7704450115},
{"learn":[3.855137428],"iteration":527,"passed_time":0.8599160829,"remaining_time":0.768712862},
{"learn":[3.851985706],"iteration":528,"passed_time":0.8613081223,"remaining_time":0.7668735834},
{"learn":[3.851051809],"iteration":529,"passed_time":0.8626111305,"remaining_time":0.7649570403},
{"learn":[3.850679146],"iteration":530,"passed_time":0.8640659153,"remaining_time":0.7631768631},
{"learn":[3.848179484],"iteration":531,"passed_time":0.8653825327,"remaining_time":0.7612763634},
{"learn":[3.844551071],"iteration":532,"passed_time":0.8666619372,"remaining_time":0.7593454497},
{"learn":[3.841604794],"iteration":533,"passed_time":0.8681443159,"remaining_time":0.7575941034},
{"learn":[3.83969656],"iteration":534,"passed_time":0.8694064174,"remaining_time":0.7556523067},
{"learn":[3.836811463],"iteration":535,"passed_time":0.8708010083,"remaining_time":0.7538277386},
{"learn":[3.834182551],"iteration":536,"passed_time":0.8721426226,"remaining_time":0.7519590955},
{"learn":[3.828012842],"iteration":537,"passed_time":0.873690413,"remaining_time":0.7502694625},
{"learn":[3.826636176],"iteration":538,"passed_time":0.8751913181,"remaining_time":0.7485402553},
{"learn":[3.826189798],"iteration":539,"passed_time":0.8764909931,"remaining_time":0.7466404756},
{"learn":[3.824104738],"iteration":540,"passed_time":0.8778259257,"remaining_time":0.7447728279},
{"learn":[3.82300218],"iteration":541,"passed_time":0.8793891593,"remaining_time":0.7431000645},
{"learn":[3.817146402],"iteration":542,"passed_time":0.8808825599,"remaining_time":0.7413689316},
{"learn":[3.814638044],"iteration":543,"passed_time":0.8821688518,"remaining_time":0.7394650669},
{"learn":[3.812979573],"iteration":544,"passed_time":0.883980548,"remaining_time":0.7380021089},
{"learn":[3.811938825],"iteration":545,"passed_time":0.8854108578,"remaining_time":0.7362207499},
{"learn":[3.811479418],"iteration":546,"passed_time":0.8867484971,"remaining_time":0.734363929},
{"learn":[3.80742981],"iteration":547,"passed_time":0.8882719681,"remaining_time":0.7326622802},
{"learn":[3.805097043],"iteration":548,"passed_time":0.8897908972,"remaining_time":0.7309575494},
{"learn":[3.801577232],"iteration":549,"passed_time":0.8911914574,"remaining_time":0.729156647},
{"learn":[3.799762083],"iteration":550,"passed_time":0.8927500046,"remaining_time":0.7274859384},
{"learn":[3.796393455],"iteration":551,"passed_time":0.8942494207,"remaining_time":0.7257676458},
{"learn":[3.793486459],"iteration":552,"passed_time":0.895554484,"remaining_time":0.7238930458},
{"learn":[3.792006091],"iteration":553,"passed_time":0.8968482095,"remaining_time":0.7220113744},
{"learn":[3.78932128],"iteration":554,"passed_time":0.8982369054,"remaining_time":0.7202079692},
{"learn":[3.787581812],"iteration":555,"passed_time":0.8995061951,"remaining_time":0.7183107025},
{"learn":[3.785308865],"iteration":556,"passed_time":0.9009414065,"remaining_time":0.7165476536},
{"learn":[3.78465475],"iteration":557,"passed_time":0.9024579244,"remaining_time":0.7148501839},
{"learn":[3.780498869],"iteration":558,"passed_time":0.9037261366,"remaining_time":0.7129574709},
{"learn":[3.778734909],"iteration":559,"passed_time":0.9050234604,"remaining_time":0.7110898617},
{"learn":[3.778652349],"iteration":560,"passed_time":0.9064000517,"remaining_time":0.709286315},
{"learn":[3.777928006],"iteration":561,"passed_time":0.9077065838,"remaining_time":0.7074296863},
{"learn":[3.776131406],"iteration":562,"passed_time":0.9091405822,"remaining_time":0.705673951},
{"learn":[3.772925617],"iteration":563,"passed_time":0.9104457409,"remaining_time":0.7038197571},
{"learn":[3.7727745],"iteration":564,"passed_time":0.9116465807,"remaining_time":0.7018871904},
{"learn":[3.771763073],"iteration":565,"passed_time":0.9130039234,"remaining_time":0.7000772133},
{"learn":[3.768738162],"iteration":566,"passed_time":0.914267775,"remaining_time":0.6981974366},
{"learn":[3.767220794],"iteration":567,"passed_time":0.9157317778,"remaining_time":0.6964720564},
{"learn":[3.766691102],"iteration":568,"passed_time":0.9170709008,"remaining_time":0.6946530022},
{"learn":[3.766259335],"iteration":569,"passed_time":0.918262257,"remaining_time":0.6927241588},
{"learn":[3.76116362],"iteration":570,"passed_time":0.9195974502,"remaining_time":0.6909059652},
{"learn":[3.758633056],"iteration":571,"passed_time":0.9209512396,"remaining_time":0.6891033751},
{"learn":[3.754603809],"iteration":572,"passed_time":0.9224883338,"remaining_time":0.6874389503},
{"learn":[3.754070549],"iteration":573,"passed_time":0.9237504156,"remaining_time":0.6855708659},
{"learn":[3.750534319],"iteration":574,"passed_time":0.925168344,"remaining_time":0.6838200804},
{"learn":[3.746491516],"iteration":575,"passed_time":0.9265828486,"remaining_time":0.6820679302},
{"learn":[3.744210544],"iteration":576,"passed_time":0.9280394886,"remaining_time":0.68034784},
{"learn":[3.742929991],"iteration":577,"passed_time":0.9294178589,"remaining_time":0.6785715164},
{"learn":[3.740402992],"iteration":578,"passed_time":0.9310035984,"remaining_time":0.6769473488},
{"learn":[3.739644243],"iteration":579,"passed_time":0.9323617786,"remaining_time":0.6751585294},
{"learn":[3.737529404],"iteration":580,"passed_time":0.9341076962,"remaining_time":0.673650817},
{"learn":[3.737196923],"iteration":581,"passed_time":0.9355324565,"remaining_time":0.6719116268},
{"learn":[3.733954464],"iteration":582,"passed_time":0.9369654025,"remaining_time":0.6701793703},
{"learn":[3.731608623],"iteration":583,"passed_time":0.9383002798,"remaining_time":0.6683782815},
{"learn":[3.729843952],"iteration":584,"passed_time":0.9395683312,"remaining_time":0.6665313803},
{"learn":[3.727223798],"iteration":585,"passed_time":0.9410310761,"remaining_time":0.6648240026},
{"learn":[3.725351667],"iteration":586,"passed_time":0.9423327862,"remaining_time":0.6630041579},
{"learn":[3.725026912],"iteration":587,"passed_time":0.9438744366,"remaining_time":0.661354197},
{"learn":[3.721974565],"iteration":588,"passed_time":0.9455581045,"remaining_time":0.6598037028},
{"learn":[3.720269493],"iteration":589,"passed_time":0.9474986246,"remaining_time":0.6584312476},
{"learn":[3.718907466],"iteration":590,"passed_time":0.9489323125,"remaining_time":0.6567061181},
{"learn":[3.715602912],"iteration":591,"passed_time":0.9502776308,"remaining_time":0.6549210699},
{"learn":[3.714463059],"iteration":592,"passed_time":0.9517976827,"remaining_time":0.6532574315},
{"learn":[3.710802077],"iteration":593,"passed_time":0.9531367452,"remaining_time":0.65147057},
{"learn":[3.708032435],"iteration":594,"passed_time":0.9547353825,"remaining_time":0.649861899},
{"learn":[3.703788939],"iteration":595,"passed_time":0.9561320287,"remaining_time":0.6481163416},
{"learn":[3.702500944],"iteration":596,"passed_time":0.9575770445,"remaining_time":0.6464046046},
{"learn":[3.698196925],"iteration":597,"passed_time":0.9590474125,"remaining_time":0.6447108024},
{"learn":[3.69658891],"iteration":598,"passed_time":0.9604179236,"remaining_time":0.6429508971},
{"learn":[3.696124066],"iteration":599,"passed_time":0.9619132038,"remaining_time":0.6412754692},
{"learn":[3.693537052],"iteration":600,"passed_time":0.9636296931,"remaining_time":0.6397475001},
{"learn":[3.691343275],"iteration":601,"passed_time":0.9650925331,"remaining_time":0.6380512096},
{"learn":[3.690973831],"iteration":602,"passed_time":0.9668794873,"remaining_time":0.636569082},
{"learn":[3.686151073],"iteration":603,"passed_time":0.9683466981,"remaining_time":0.634876312},
{"learn":[3.683921982],"iteration":604,"passed_time":0.9696206894,"remaining_time":0.633058136},
{"learn":[3.679975271],"iteration":605,"passed_time":0.9711487011,"remaining_time":0.6314069112},
{"learn":[3.674047638],"iteration":606,"passed_time":0.9726911482,"remaining_time":0.6297654386},
{"learn":[3.673151794],"iteration":607,"passed_time":0.9741667252,"remaining_time":0.6280811781},
{"learn":[3.670953108],"iteration":608,"passed_time":0.9755981973,"remaining_time":0.626369286},
{"learn":[3.6703947],"iteration":609,"passed_time":0.9769183231,"remaining_time":0.6245871246},
{"learn":[3.668433805],"iteration":610,"passed_time":0.9783631985,"remaining_time":0.6228858989},
{"learn":[3.668304956],"iteration":611,"passed_time":0.9798425194,"remaining_time":0.6212073489},
{"learn":[3.667880012],"iteration":612,"passed_time":0.9811408966,"remaining_time":0.6194152153},
{"learn":[3.667282264],"iteration":613,"passed_time":0.9823691645,"remaining_time":0.6175806148},
{"learn":[3.664611483],"iteration":614,"passed_time":0.9836834206,"remaining_time":0.6158018162},
{"learn":[3.662543394],"iteration":615,"passed_time":0.9850089896,"remaining_time":0.6140315779},
{"learn":[3.659041959],"iteration":616,"passed_time":0.9863284893,"remaining_time":0.6122590136},
{"learn":[3.656868545],"iteration":617,"passed_time":0.9876280641,"remaining_time":0.6104755995},
{"learn":[3.654785614],"iteration":618,"passed_time":0.9888377058,"remaining_time":0.608638394},
{"learn":[3.654566096],"iteration":619,"passed_time":0.9900692418,"remaining_time":0.606816632},
{"learn":[3.651007045],"iteration":620,"passed_time":0.9913201759,"remaining_time":0.6050086098},
{"learn":[3.648921786],"iteration":621,"passed_time":0.9925108304,"remaining_time":0.6031657458},
{"learn":[3.647655706],"iteration":622,"passed_time":0.9936699868,"remaining_time":0.601305915},
{"learn":[3.647241144],"iteration":623,"passed_time":0.9948536139,"remaining_time":0.599463075},
{"learn":[3.644195689],"iteration":624,"passed_time":0.9960692604,"remaining_time":0.5976415563},
{"learn":[3.642632246],"iteration":625,"passed_time":0.9973443044,"remaining_time":0.5958574598},
{"learn":[3.642523322],"iteration":626,"passed_time":0.9983488671,"remaining_time":0.5939140788},
{"learn":[3.641494659],"iteration":627,"passed_time":0.9996281616,"remaining_time":0.5921364269},
{"learn":[3.63976496],"iteration":628,"passed_time":1.000978412,"remaining_time":0.5904022113},
{"learn":[3.637945652],"iteration":629,"passed_time":1.002563019,"remaining_time":0.5888068525},
{"learn":[3.636233667],"iteration":630,"passed_time":1.003852895,"remaining_time":0.5870391732},
{"learn":[3.635304404],"iteration":631,"passed_time":1.005164239,"remaining_time":0.5852855063},
{"learn":[3.632234951],"iteration":632,"passed_time":1.006496996,"remaining_time":0.5835456518},
{"learn":[3.631630987],"iteration":633,"passed_time":1.007817032,"remaining_time":0.5817997376},
{"learn":[3.630301009],"iteration":634,"passed_time":1.009297611,"remaining_time":0.5801474454},
{"learn":[3.629077964],"iteration":635,"passed_time":1.010830119,"remaining_time":0.5785254138},
{"learn":[3.628004522],"iteration":636,"passed_time":1.012238684,"remaining_time":0.5768330331},
{"learn":[3.625062876],"iteration":637,"passed_time":1.013739126,"remaining_time":0.5751936736},
{"learn":[3.624917986],"iteration":638,"passed_time":1.01501793,"remaining_time":0.5734295346},
{"learn":[3.622887087],"iteration":639,"passed_time":1.016431748,"remaining_time":0.5717428583},
{"learn":[3.621220865],"iteration":640,"passed_time":1.017887415,"remaining_time":0.570080471},
{"learn":[3.621143844],"iteration":641,"passed_time":1.019225701,"remaining_time":0.5683532725},
{"learn":[3.620822821],"iteration":642,"passed_time":1.020714259,"remaining_time":0.5667107163},
{"learn":[3.619202826],"iteration":643,"passed_time":1.022098715,"remaining_time":0.565011091},
{"learn":[3.618204882],"iteration":644,"passed_time":1.023454916,"remaining_time":0.5632968915},
{"learn":[3.614259666],"iteration":645,"passed_time":1.024665951,"remaining_time":0.5615042516},
{"learn":[3.613415661],"iteration":646,"passed_time":1.025987565,"remaining_time":0.559773741},
{"learn":[3.611096773],"iteration":647,"passed_time":1.027399193,"remaining_time":0.5580933888},
{"learn":[3.610820695],"iteration":648,"passed_time":1.028789403,"remaining_time":0.556402281},
{"learn":[3.609290065],"iteration":649,"passed_time":1.030153573,"remaining_time":0.5546980776},
{"learn":[3.60897947],"iteration":650,"passed_time":1.031480365,"remaining_time":0.5529748808},
{"learn":[3.606570702],"iteration":651,"passed_time":1.032827363,"remaining_time":0.5512636844},
{"learn":[3.606292637],"iteration":652,"passed_time":1.034064703,"remaining_time":0.5494953323},
{"learn":[3.602753838],"iteration":653,"passed_time":1.035245232,"remaining_time":0.5476985481},
{"learn":[3.599755869],"iteration":654,"passed_time":1.036662203,"remaining_time":0.5460281833},
{"learn":[3.599509575],"iteration":655,"passed_time":1.038055967,"remaining_time":0.5443464218},
{"learn":[3.595337722],"iteration":656,"passed_time":1.039323763,"remaining_time":0.5425997728},
{"learn":[3.595168561],"iteration":657,"passed_time":1.040624832,"remaining_time":0.540871873},
{"learn":[3.59290559],"iteration":658,"passed_time":1.042102067,"remaining_time":0.5392364263},
{"learn":[3.592015928],"iteration":659,"passed_time":1.043457766,"remaining_time":0.5375388493},
{"learn":[3.590680403],"iteration":660,"passed_time":1.044897725,"remaining_time":0.5358855198},
{"learn":[3.590361532],"iteration":661,"passed_time":1.046249128,"remaining_time":0.5341876212},
{"learn":[3.589069739],"iteration":662,"passed_time":1.047567008,"remaining_time":0.5324737281},
{"learn":[3.585010186],"iteration":663,"passed_time":1.048894252,"remaining_time":0.5307657659},
{"learn":[3.582997552],"iteration":664,"passed_time":1.05025792,"remaining_time":0.5290772982},
{"learn":[3.582119256],"iteration":665,"passed_time":1.051641303,"remaining_time":0.5273996926},
{"learn":[3.579019356],"iteration":666,"passed_time":1.053032942,"remaining_time":0.5257270908},
{"learn":[3.57719559],"iteration":667,"passed_time":1.054250533,"remaining_time":0.5239688277},
{"learn":[3.574050046],"iteration":668,"passed_time":1.055604498,"remaining_time":0.5222796542},
{"learn":[3.572204518],"iteration":669,"passed_time":1.057026922,"remaining_time":0.5206252006},
{"learn":[3.569508025],"iteration":670,"passed_time":1.058529391,"remaining_time":0.5190106848},
{"learn":[3.566268704],"iteration":671,"passed_time":1.060042555,"remaining_time":0.5174017232},
{"learn":[3.562564052],"iteration":672,"passed_time":1.061434991,"remaining_time":0.5157343863},
{"learn":[3.561173586],"iteration":673,"passed_time":1.062682636,"remaining_time":0.513997833},
{"learn":[3.559551904],"iteration":674,"passed_time":1.064199801,"remaining_time":0.5123924968},
{"learn":[3.558593054],"iteration":675,"passed_time":1.065573329,"remaining_time":0.510718578},
{"learn":[3.555647008],"iteration":676,"passed_time":1.066792374,"remaining_time":0.5089718418},
{"learn":[3.553100059],"iteration":677,"passed_time":1.067932443,"remaining_time":0.5071891545},
{"learn":[3.55085578],"iteration":678,"passed_time":1.069082257,"remaining_time":0.5054129667},
{"learn":[3.550737965],"iteration":679,"passed_time":1.070182166,"remaining_time":0.5036151369},
{"learn":[3.549408772],"iteration":680,"passed_time":1.071369232,"remaining_time":0.5018601834},
{"learn":[3.547390589],"iteration":681,"passed_time":1.072556327,"remaining_time":0.5001069092},
{"learn":[3.54723575],"iteration":682,"passed_time":1.073656427,"remaining_time":0.4983149156},
{"learn":[3.543988891],"iteration":683,"passed_time":1.074849949,"remaining_time":0.496568105},
{"learn":[3.543868508],"iteration":684,"passed_time":1.075960785,"remaining_time":0.4947848866},
{"learn":[3.542752124],"iteration":685,"passed_time":1.077098007,"remaining_time":0.4930157059},
{"learn":[3.541334315],"iteration":686,"passed_time":1.078326054,"remaining_time":0.4912897453},
{"learn":[3.540208266],"iteration":687,"passed_time":1.079537711,"remaining_time":0.4895577992},
{"learn":[3.537730983],"iteration":688,"passed_time":1.080799221,"remaining_time":0.4878498663},
{"learn":[3.53419867],"iteration":689,"passed_time":1.082000573,"remaining_time":0.4861161993},
{"learn":[3.532628335],"iteration":690,"passed_time":1.08328745,"remaining_time":0.4844223186},
{"learn":[3.532204987],"iteration":691,"passed_time":1.084605677,"remaining_time":0.4827435672},
{"learn":[3.530618147],"iteration":692,"passed_time":1.085939401,"remaining_time":0.4810727218},
{"learn":[3.528909306],"iteration":693,"passed_time":1.087300559,"remaining_time":0.4794149437},
{"learn":[3.526700678],"iteration":694,"passed_time":1.088700428,"remaining_time":0.4777750079},
{"learn":[3.526439574],"iteration":695,"passed_time":1.08991664,"remaining_time":0.476055544},
{"learn":[3.525784216],"iteration":696,"passed_time":1.091258265,"remaining_time":0.4743920434},
{"learn":[3.524112693],"iteration":697,"passed_time":1.092584681,"remaining_time":0.4727228849},
{"learn":[3.522813541],"iteration":698,"passed_time":1.093998229,"remaining_time":0.4710922273},
{"learn":[3.519148203],"iteration":699,"passed_time":1.095274245,"remaining_time":0.4694032479},
{"learn":[3.517236747],"iteration":700,"passed_time":1.096580381,"remaining_time":0.4677282939},
{"learn":[3.515603888],"iteration":701,"passed_time":1.097873209,"remaining_time":0.4660487413},
{"learn":[3.51263524],"iteration":702,"passed_time":1.099168899,"remaining_time":0.464371498},
{"learn":[3.51123442],"iteration":703,"passed_time":1.100496163,"remaining_time":0.462708614},
{"learn":[3.50828027],"iteration":704,"passed_time":1.101732431,"remaining_time":0.4610086058},
{"learn":[3.508265537],"iteration":705,"passed_time":1.102472718,"remaining_time":0.4591033697},
{"learn":[3.506774876],"iteration":706,"passed_time":1.103605499,"remaining_time":0.4573640893},
{"learn":[3.50552068],"iteration":707,"passed_time":1.104846318,"remaining_time":0.4556710802},
{"learn":[3.501973993],"iteration":708,"passed_time":1.106148559,"remaining_time":0.4540045567},
{"learn":[3.498880354],"iteration":709,"passed_time":1.107648902,"remaining_time":0.4524199741},
{"learn":[3.497370959],"iteration":710,"passed_time":1.109029388,"remaining_time":0.45078691},
{"learn":[3.496050455],"iteration":711,"passed_time":1.110217927,"remaining_time":0.4490769143},
{"learn":[3.495630067],"iteration":712,"passed_time":1.111551085,"remaining_time":0.4474265939},
{"learn":[3.49550669],"iteration":713,"passed_time":1.112867537,"remaining_time":0.4457704701},
{"learn":[3.493652375],"iteration":714,"passed_time":1.114357815,"remaining_time":0.4441845837},
{"learn":[3.491915684],"iteration":715,"passed_time":1.115776706,"remaining_time":0.4425706488},
{"learn":[3.490303956],"iteration":716,"passed_time":1.116889678,"remaining_time":0.4408365117},
{"learn":[3.488363853],"iteration":717,"passed_time":1.118085926,"remaining_time":0.4391368123},
{"learn":[3.485483936],"iteration":718,"passed_time":1.119489008,"remaining_time":0.4375193481},
{"learn":[3.483763466],"iteration":719,"passed_time":1.120736484,"remaining_time":0.4358419658},
{"learn":[3.481642352],"iteration":720,"passed_time":1.12226076,"remaining_time":0.4342728879},
{"learn":[3.479826119],"iteration":721,"passed_time":1.123640209,"remaining_time":0.4326481691},
{"learn":[3.478588728],"iteration":722,"passed_time":1.124905854,"remaining_time":0.4309805278},
{"learn":[3.475390887],"iteration":723,"passed_time":1.126128298,"remaining_time":0.4292975278},
{"learn":[3.472636852],"iteration":724,"passed_time":1.127484393,"remaining_time":0.4276664937},
{"learn":[3.47061883],"iteration":725,"passed_time":1.1287608,"remaining_time":0.4260061421},
{"learn":[3.46953149],"iteration":726,"passed_time":1.130108805,"remaining_time":0.4243737328},
{"learn":[3.467217162],"iteration":727,"passed_time":1.131407989,"remaining_time":0.4227238639},
{"learn":[3.465686216],"iteration":728,"passed_time":1.132733618,"remaining_time":0.4210847881},
{"learn":[3.462631216],"iteration":729,"passed_time":1.133921055,"remaining_time":0.4193954586},
{"learn":[3.461451053],"iteration":730,"passed_time":1.13534172,"remaining_time":0.4177933279},
{"learn":[3.458950469],"iteration":731,"passed_time":1.136562319,"remaining_time":0.4161184446},
{"learn":[3.458072145],"iteration":732,"passed_time":1.137793614,"remaining_time":0.4144486971},
{"learn":[3.454364268],"iteration":733,"passed_time":1.139023957,"remaining_time":0.4127797992},
{"learn":[3.453243406],"iteration":734,"passed_time":1.140180277,"remaining_time":0.4110854059},
{"learn":[3.453017963],"iteration":735,"passed_time":1.141444228,"remaining_time":0.4094310817},
{"learn":[3.45201581],"iteration":736,"passed_time":1.142746459,"remaining_time":0.4077914773},
{"learn":[3.449510107],"iteration":737,"passed_time":1.143962592,"remaining_time":0.4061222211},
{"learn":[3.447189189],"iteration":738,"passed_time":1.145299875,"remaining_time":0.4044969789},
{"learn":[3.446423605],"iteration":739,"passed_time":1.146638146,"remaining_time":0.4028728622},
{"learn":[3.445531987],"iteration":740,"passed_time":1.14802811,"remaining_time":0.4012675852},
{"learn":[3.445328199],"iteration":741,"passed_time":1.149221607,"remaining_time":0.3995945748},
{"learn":[3.443327544],"iteration":742,"passed_time":1.150584574,"remaining_time":0.3979814745},
{"learn":[3.441475798],"iteration":743,"passed_time":1.151919366,"remaining_time":0.3963593519},
{"learn":[3.439046501],"iteration":744,"passed_time":1.153151073,"remaining_time":0.3947027162},
{"learn":[3.435899469],"iteration":745,"passed_time":1.1543912,"remaining_time":0.3930500869},
{"learn":[3.433988352],"iteration":746,"passed_time":1.155707787,"remaining_time":0.391424458},
{"learn":[3.433413263],"iteration":747,"passed_time":1.157059451,"remaining_time":0.3898114729},
{"learn":[3.429944699],"iteration":748,"passed_time":1.158423496,"remaining_time":0.3882033344},
{"learn":[3.429291634],"iteration":749,"passed_time":1.159580081,"remaining_time":0.3865266935},
{"learn":[3.429175603],"iteration":750,"passed_time":1.161022716,"remaining_time":0.3849462799},
{"learn":[3.428780323],"iteration":751,"passed_time":1.162425933,"remaining_time":0.3833532331},
{"learn":[3.423893341],"iteration":752,"passed_time":1.163814052,"remaining_time":0.3817557383},
{"learn":[3.421024316],"iteration":753,"passed_time":1.165078249,"remaining_time":0.3801183678},
{"learn":[3.420969872],"iteration":754,"passed_time":1.166432951,"remaining_time":0.3785113549},
{"learn":[3.419544785],"iteration":755,"passed_time":1.167836689,"remaining_time":0.3769208362},
{"learn":[3.417057977],"iteration":756,"passed_time":1.169214869,"remaining_time":0.3753226065},
{"learn":[3.415160245],"iteration":757,"passed_time":1.170673669,"remaining_time":0.3737506964},
{"learn":[3.412854597],"iteration":758,"passed_time":1.171987078,"remaining_time":0.3721329194},
{"learn":[3.410926347],"iteration":759,"passed_time":1.173362581,"remaining_time":0.370535552},
{"learn":[3.408963843],"iteration":760,"passed_time":1.174692767,"remaining_time":0.3689245352},
{"learn":[3.407629634],"iteration":761,"passed_time":1.175978296,"remaining_time":0.3673003078},
{"learn":[3.404384724],"iteration":762,"passed_time":1.177432184,"remaining_time":0.365729263},
{"learn":[3.403041656],"iteration":763,"passed_time":1.178831201,"remaining_time":0.3641415752},
{"learn":[3.401101731],"iteration":764,"passed_time":1.180354371,"remaining_time":0.3625925191},
{"learn":[3.400890668],"iteration":765,"passed_time":1.181646136,"remaining_time":0.3609728405},
{"learn":[3.399289941],"iteration":766,"passed_time":1.18306456,"remaining_time":0.3593924935},
{"learn":[3.399202366],"iteration":767,"passed_time":1.184526062,"remaining_time":0.3578255813},
{"learn":[3.397447845],"iteration":768,"passed_time":1.18583699,"remaining_time":0.3562137122},
{"learn":[3.394655341],"iteration":769,"passed_time":1.187367899,"remaining_time":0.3546683334},
{"learn":[3.393228229],"iteration":770,"passed_time":1.188736294,"remaining_time":0.353074723},
{"learn":[3.389691197],"iteration":771,"passed_time":1.190129246,"remaining_time":0.3514889482},
{"learn":[3.389626772],"iteration":772,"passed_time":1.191462038,"remaining_time":0.349886006},
{"learn":[3.388480222],"iteration":773,"passed_time":1.192893219,"remaining_time":0.3483124904},
{"learn":[3.388215066],"iteration":774,"passed_time":1.194085548,"remaining_time":0.3466699979},
{"learn":[3.386324358],"iteration":775,"passed_time":1.195334457,"remaining_time":0.345044998},
{"learn":[3.383913061],"iteration":776,"passed_time":1.19664114,"remaining_time":0.3434375472},
{"learn":[3.382839768],"iteration":777,"passed_time":1.197969336,"remaining_time":0.3418370083},
{"learn":[3.381961844],"iteration":778,"passed_time":1.199259056,"remaining_time":0.3402262533},
{"learn":[3.381521703],"iteration":779,"passed_time":1.200568359,"remaining_time":0.338621845},
{"learn":[3.380918963],"iteration":780,"passed_time":1.201876536,"remaining_time":0.3370178762},
{"learn":[3.377139006],"iteration":781,"passed_time":1.203136968,"remaining_time":0.3354013543},
{"learn":[3.376004372],"iteration":782,"passed_time":1.204478723,"remaining_time":0.3338082795},
{"learn":[3.373826468],"iteration":783,"passed_time":1.205869368,"remaining_time":0.3322293158},
{"learn":[3.373546786],"iteration":784,"passed_time":1.207118243,"remaining_time":0.3306120027},
{"learn":[3.372109181],"iteration":785,"passed_time":1.208512071,"remaining_time":0.3290350932},
{"learn":[3.370764924],"iteration":786,"passed_time":1.209793706,"remaining_time":0.3274282839},
{"learn":[3.367833107],"iteration":787,"passed_time":1.21098415,"remaining_time":0.3257977663},
{"learn":[3.36450404],"iteration":788,"passed_time":1.212250773,"remaining_time":0.3241887366},
{"learn":[3.361794558],"iteration":789,"passed_time":1.213587992,"remaining_time":0.3225993395},
{"learn":[3.356880529],"iteration":790,"passed_time":1.214837677,"remaining_time":0.320987452},
{"learn":[3.353843509],"iteration":791,"passed_time":1.216203928,"remaining_time":0.3194070921},
{"learn":[3.353640253],"iteration":792,"passed_time":1.217574534,"remaining_time":0.3178284092},
{"learn":[3.353055088],"iteration":793,"passed_time":1.218776918,"remaining_time":0.3162066058},
{"learn":[3.351415617],"iteration":794,"passed_time":1.220153207,"remaining_time":0.3146307013},
{"learn":[3.349169061],"iteration":795,"passed_time":1.221569632,"remaining_time":0.3130655841},
{"learn":[3.346211014],"iteration":796,"passed_time":1.223019504,"remaining_time":0.3115093593},
{"learn":[3.344560452],"iteration":797,"passed_time":1.224362116,"remaining_time":0.3099262499},
{"learn":[3.344445461],"iteration":798,"passed_time":1.225712222,"remaining_time":0.3083456277},
{"learn":[3.342608898],"iteration":799,"passed_time":1.227007851,"remaining_time":0.3067519628},
{"learn":[3.339572899],"iteration":800,"passed_time":1.228426521,"remaining_time":0.3051896101},
{"learn":[3.339309302],"iteration":801,"passed_time":1.229678789,"remaining_time":0.3035865339},
{"learn":[3.33698088],"iteration":802,"passed_time":1.230982113,"remaining_time":0.301996857},
{"learn":[3.334746342],"iteration":803,"passed_time":1.232351662,"remaining_time":0.3004240369},
{"learn":[3.332048511],"iteration":804,"passed_time":1.233607017,"remaining_time":0.2988240599},
{"learn":[3.331932544],"iteration":805,"passed_time":1.234959182,"remaining_time":0.2972482398},
{"learn":[3.330541133],"iteration":806,"passed_time":1.236373742,"remaining_time":0.2956878961},
{"learn":[3.329124989],"iteration":807,"passed_time":1.237687337,"remaining_time":0.2941039216},
{"learn":[3.32583918],"iteration":808,"passed_time":1.238984801,"remaining_time":0.2925168072},
{"learn":[3.325287299],"iteration":809,"passed_time":1.240402148,"remaining_time":0.2909585286},
{"learn":[3.322745162],"iteration":810,"passed_time":1.241696861,"remaining_time":0.2893720182},
{"learn":[3.319733662],"iteration":811,"passed_time":1.243040686,"remaining_time":0.2877975972},
{"learn":[3.318080007],"iteration":812,"passed_time":1.244387287,"remaining_time":0.2862243822},
{"learn":[3.317179538],"iteration":813,"passed_time":1.245773547,"remaining_time":0.2846607859},
{"learn":[3.315685949],"iteration":814,"passed_time":1.24709267,"remaining_time":0.2830823853},
{"learn":[3.314944576],"iteration":815,"passed_time":1.248737612,"remaining_time":0.281578089},
{"learn":[3.312369052],"iteration":816,"passed_time":1.2501916,"remaining_time":0.2800306767},
{"learn":[3.312321621],"iteration":817,"passed_time":1.251361708,"remaining_time":0.2784203312},
{"learn":[3.309465776],"iteration":818,"passed_time":1.252766429,"remaining_time":0.2768629105},
{"learn":[3.308307377],"iteration":819,"passed_time":1.25409637,"remaining_time":0.275289447},
{"learn":[3.308076804],"iteration":820,"passed_time":1.255417798,"remaining_time":0.273714721},
{"learn":[3.305643326],"iteration":821,"passed_time":1.257077256,"remaining_time":0.2722138097},
{"learn":[3.304154814],"iteration":822,"passed_time":1.258391447,"remaining_time":0.2706382578},
{"learn":[3.303076321],"iteration":823,"passed_time":1.259772915,"remaining_time":0.2690777101},
{"learn":[3.301746372],"iteration":824,"passed_time":1.261312716,"remaining_time":0.2675511822},
{"learn":[3.301345455],"iteration":825,"passed_time":1.262851189,"remaining_time":0.2660243425},
{"learn":[3.299181039],"iteration":826,"passed_time":1.264125451,"remaining_time":0.2644422044},
{"learn":[3.297989357],"iteration":827,"passed_time":1.265584446,"remaining_time":0.2628991844},
{"learn":[3.294775182],"iteration":828,"passed_time":1.267043918,"remaining_time":0.2613564656},
{"learn":[3.293840636],"iteration":829,"passed_time":1.268407607,"remaining_time":0.2597943291},
{"learn":[3.289279397],"iteration":830,"passed_time":1.269735326,"remaining_time":0.2582253551},
{"learn":[3.286204979],"iteration":831,"passed_time":1.271080068,"remaining_time":0.2566603984},
{"learn":[3.284833593],"iteration":832,"passed_time":1.272355423,"remaining_time":0.2550820596},
{"learn":[3.283519914],"iteration":833,"passed_time":1.273609746,"remaining_time":0.2535002611},
{"learn":[3.282853026],"iteration":834,"passed_time":1.275061227,"remaining_time":0.2519582066},
{"learn":[3.281944673],"iteration":835,"passed_time":1.27638396,"remaining_time":0.2503911117},
{"learn":[3.279764865],"iteration":836,"passed_time":1.277793793,"remaining_time":0.248841563},
{"learn":[3.277468839],"iteration":837,"passed_time":1.279365924,"remaining_time":0.2473237228},
{"learn":[3.277124974],"iteration":838,"passed_time":1.280659148,"remaining_time":0.2457522323},
{"learn":[3.275636037],"iteration":839,"passed_time":1.282076776,"remaining_time":0.2442051002},
{"learn":[3.274413635],"iteration":840,"passed_time":1.283471537,"remaining_time":0.2426539529},
{"learn":[3.272636087],"iteration":841,"passed_time":1.284908232,"remaining_time":0.2411110459},
{"learn":[3.269644466],"iteration":842,"passed_time":1.286716404,"remaining_time":0.2396375746},
{"learn":[3.26852083],"iteration":843,"passed_time":1.288210456,"remaining_time":0.2381052502},
{"learn":[3.267820927],"iteration":844,"passed_time":1.289635593,"remaining_time":0.236560375},
{"learn":[3.267331099],"iteration":845,"passed_time":1.291115881,"remaining_time":0.2350258222},
{"learn":[3.267231014],"iteration":846,"passed_time":1.292562561,"remaining_time":0.2334853268},
{"learn":[3.267158695],"iteration":847,"passed_time":1.293881794,"remaining_time":0.2319222084},
{"learn":[3.264718705],"iteration":848,"passed_time":1.295358639,"remaining_time":0.2303876967},
{"learn":[3.261678512],"iteration":849,"passed_time":1.296701587,"remaining_time":0.2288296918},
{"learn":[3.261368381],"iteration":850,"passed_time":1.297975217,"remaining_time":0.2272600557},
{"learn":[3.260128799],"iteration":851,"passed_time":1.299277419,"remaining_time":0.2256960774},
{"learn":[3.258972952],"iteration":852,"passed_time":1.300657979,"remaining_time":0.2241462168},
{"learn":[3.258724846],"iteration":853,"passed_time":1.302109396,"remaining_time":0.2226088663},
{"learn":[3.25686724],"iteration":854,"passed_time":1.303482748,"remaining_time":0.2210584778},
{"learn":[3.255750259],"iteration":855,"passed_time":1.304861245,"remaining_time":0.2195093682},
{"learn":[3.254915866],"iteration":856,"passed_time":1.306272641,"remaining_time":0.2179661467},
{"learn":[3.254348625],"iteration":857,"passed_time":1.307664756,"remaining_time":0.2164200412},
{"learn":[3.253408514],"iteration":858,"passed_time":1.309013217,"remaining_time":0.2148671288},
{"learn":[3.253291714],"iteration":859,"passed_time":1.310235972,"remaining_time":0.2132942279},
{"learn":[3.250186342],"iteration":860,"passed_time":1.311491116,"remaining_time":0.2117273695},
{"learn":[3.249141318],"iteration":861,"passed_time":1.312860835,"remaining_time":0.2101795768},
{"learn":[3.246300388],"iteration":862,"passed_time":1.314252799,"remaining_time":0.2086357283},
{"learn":[3.245205135],"iteration":863,"passed_time":1.315840143,"remaining_time":0.2071229855},
{"learn":[3.244403535],"iteration":864,"passed_time":1.317089834,"remaining_time":0.2055573729},
{"learn":[3.244211781],"iteration":865,"passed_time":1.318355654,"remaining_time":0.2039949858},
{"learn":[3.242286347],"iteration":866,"passed_time":1.319648724,"remaining_time":0.2024374628},
{"learn":[3.239606746],"iteration":867,"passed_time":1.320942694,"remaining_time":0.2008806862},
{"learn":[3.236773361],"iteration":868,"passed_time":1.322360913,"remaining_time":0.1993432447},
{"learn":[3.234552446],"iteration":869,"passed_time":1.323638654,"remaining_time":0.1977850862},
{"learn":[3.233724647],"iteration":870,"passed_time":1.324993125,"remaining_time":0.1962389359},
{"learn":[3.230851485],"iteration":871,"passed_time":1.326245302,"remaining_time":0.1946782095},
{"learn":[3.227728941],"iteration":872,"passed_time":1.327662479,"remaining_time":0.1931421934},
{"learn":[3.225787575],"iteration":873,"passed_time":1.328926406,"remaining_time":0.191584356},
{"learn":[3.222797487],"iteration":874,"passed_time":1.330386599,"remaining_time":0.1900552284},
{"learn":[3.22137014],"iteration":875,"passed_time":1.331623828,"remaining_time":0.1884946972},
{"learn":[3.219701963],"iteration":876,"passed_time":1.33297842,"remaining_time":0.1869513634},
{"learn":[3.21783327],"iteration":877,"passed_time":1.334270607,"remaining_time":0.1853997882},
{"learn":[3.217713355],"iteration":878,"passed_time":1.3354204,"remaining_time":0.1838292018},
{"learn":[3.217666091],"iteration":879,"passed_time":1.336725152,"remaining_time":0.1822807026},
{"learn":[3.214962005],"iteration":880,"passed_time":1.338250072,"remaining_time":0.1807624955},
{"learn":[3.214081828],"iteration":881,"passed_time":1.339485071,"remaining_time":0.1792054857},
{"learn":[3.213358337],"iteration":882,"passed_time":1.341003559,"remaining_time":0.1776867683},
{"learn":[3.210850401],"iteration":883,"passed_time":1.342366747,"remaining_time":0.1761476727},
{"learn":[3.207810328],"iteration":884,"passed_time":1.343652718,"remaining_time":0.1745989408},
{"learn":[3.204935073],"iteration":885,"passed_time":1.344867547,"remaining_time":0.1730416483},
{"learn":[3.20280198],"iteration":886,"passed_time":1.346353851,"remaining_time":0.1715197127},
{"learn":[3.200663495],"iteration":887,"passed_time":1.347704532,"remaining_time":0.1699807518},
{"learn":[3.197301669],"iteration":888,"passed_time":1.348998909,"remaining_time":0.1684351843},
{"learn":[3.195666943],"iteration":889,"passed_time":1.350404376,"remaining_time":0.1669039117},
{"learn":[3.193886506],"iteration":890,"passed_time":1.351561317,"remaining_time":0.165342518},
{"learn":[3.190601248],"iteration":891,"passed_time":1.352918515,"remaining_time":0.1638062776},
{"learn":[3.188983797],"iteration":892,"passed_time":1.354414958,"remaining_time":0.1622871227},
{"learn":[3.187365749],"iteration":893,"passed_time":1.355660644,"remaining_time":0.1607382866},
{"learn":[3.186160771],"iteration":894,"passed_time":1.356941843,"remaining_time":0.1591942945},
{"learn":[3.185358981],"iteration":895,"passed_time":1.358583767,"remaining_time":0.1576927587},
{"learn":[3.183832164],"iteration":896,"passed_time":1.360037776,"remaining_time":0.1561693321},
{"learn":[3.183106966],"iteration":897,"passed_time":1.361375024,"remaining_time":0.1546327978},
{"learn":[3.182838152],"iteration":898,"passed_time":1.362684012,"remaining_time":0.1530935319},
{"learn":[3.180835453],"iteration":899,"passed_time":1.363955618,"remaining_time":0.1515506242},
{"learn":[3.179957348],"iteration":900,"passed_time":1.365328314,"remaining_time":0.1500194263},
{"learn":[3.179752966],"iteration":901,"passed_time":1.366563098,"remaining_time":0.148473596},
{"learn":[3.178851983],"iteration":902,"passed_time":1.367788659,"remaining_time":0.1469274639},
{"learn":[3.176748586],"iteration":903,"passed_time":1.369105171,"remaining_time":0.1453916996},
{"learn":[3.172960988],"iteration":904,"passed_time":1.370667708,"remaining_time":0.1438822456},
{"learn":[3.172794225],"iteration":905,"passed_time":1.372005408,"remaining_time":0.1423493469},
{"learn":[3.169996507],"iteration":906,"passed_time":1.373568932,"remaining_time":0.1408400338},
{"learn":[3.16813015],"iteration":907,"passed_time":1.37487377,"remaining_time":0.1393043908},
{"learn":[3.166920871],"iteration":908,"passed_time":1.376198577,"remaining_time":0.1377712547},
{"learn":[3.16531606],"iteration":909,"passed_time":1.377649884,"remaining_time":0.1362510874},
{"learn":[3.162035247],"iteration":910,"passed_time":1.378864417,"remaining_time":0.1347079398},
{"learn":[3.16189467],"iteration":911,"passed_time":1.380091713,"remaining_time":0.1331667442},
{"learn":[3.161008416],"iteration":912,"passed_time":1.381559896,"remaining_time":0.1316491905},
{"learn":[3.160560787],"iteration":913,"passed_time":1.382816965,"remaining_time":0.1301118808},
{"learn":[3.160416261],"iteration":914,"passed_time":1.384097343,"remaining_time":0.1285773488},
{"learn":[3.15844291],"iteration":915,"passed_time":1.385465077,"remaining_time":0.1270513826},
{"learn":[3.155040501],"iteration":916,"passed_time":1.386807638,"remaining_time":0.1255234831},
{"learn":[3.154937548],"iteration":917,"passed_time":1.388231902,"remaining_time":0.1240032854},
{"learn":[3.153721161],"iteration":918,"passed_time":1.389466691,"remaining_time":0.1224665963},
{"learn":[3.153170511],"iteration":919,"passed_time":1.39074575,"remaining_time":0.1209344131},
{"learn":[3.153113601],"iteration":920,"passed_time":1.391968028,"remaining_time":0.119397909},
{"learn":[3.150607379],"iteration":921,"passed_time":1.393254085,"remaining_time":0.1178674822},
{"learn":[3.148408359],"iteration":922,"passed_time":1.394747941,"remaining_time":0.1163549204},
{"learn":[3.147495728],"iteration":923,"passed_time":1.396141394,"remaining_time":0.1148341406},
{"learn":[3.146946235],"iteration":924,"passed_time":1.397619908,"remaining_time":0.1133205331},
{"learn":[3.14472738],"iteration":925,"passed_time":1.399066197,"remaining_time":0.1118044261},
{"learn":[3.144469477],"iteration":926,"passed_time":1.400468271,"remaining_time":0.1102849879},
{"learn":[3.142975516],"iteration":927,"passed_time":1.401875769,"remaining_time":0.1087662234},
{"learn":[3.14079113],"iteration":928,"passed_time":1.403309707,"remaining_time":0.1072497193},
{"learn":[3.138173032],"iteration":929,"passed_time":1.40465693,"remaining_time":0.1057268657},
{"learn":[3.136352813],"iteration":930,"passed_time":1.405931402,"remaining_time":0.1041989976},
{"learn":[3.133735004],"iteration":931,"passed_time":1.40735712,"remaining_time":0.1026827083},
{"learn":[3.1319496],"iteration":932,"passed_time":1.408653317,"remaining_time":0.1011573121},
{"learn":[3.129865343],"iteration":933,"passed_time":1.410026524,"remaining_time":0.09963784861},
{"learn":[3.129830206],"iteration":934,"passed_time":1.411204006,"remaining_time":0.09810509133},
{"learn":[3.126676562],"iteration":935,"passed_time":1.412468819,"remaining_time":0.09657906456},
{"learn":[3.12645665],"iteration":936,"passed_time":1.413924707,"remaining_time":0.09506644244},
{"learn":[3.126378007],"iteration":937,"passed_time":1.415260817,"remaining_time":0.09354602418},
{"learn":[3.124621914],"iteration":938,"passed_time":1.416646401,"remaining_time":0.09202921242},
{"learn":[3.123379018],"iteration":939,"passed_time":1.417936968,"remaining_time":0.09050661498},
{"learn":[3.123332451],"iteration":940,"passed_time":1.419151141,"remaining_time":0.08897972085},
{"learn":[3.122432444],"iteration":941,"passed_time":1.420471157,"remaining_time":0.08746000753},
{"learn":[3.121889006],"iteration":942,"passed_time":1.421807749,"remaining_time":0.08594171969},
{"learn":[3.121070914],"iteration":943,"passed_time":1.423238649,"remaining_time":0.08442941138},
{"learn":[3.118444705],"iteration":944,"passed_time":1.424552198,"remaining_time":0.08291044541},
{"learn":[3.116820458],"iteration":945,"passed_time":1.426012808,"remaining_time":0.08140030826},
{"learn":[3.114971041],"iteration":946,"passed_time":1.427333084,"remaining_time":0.0798824218},
{"learn":[3.114685138],"iteration":947,"passed_time":1.428620698,"remaining_time":0.07836316067},
{"learn":[3.113399363],"iteration":948,"passed_time":1.429886078,"remaining_time":0.07684319283},
{"learn":[3.110575399],"iteration":949,"passed_time":1.431222776,"remaining_time":0.07532751452},
{"learn":[3.110466553],"iteration":950,"passed_time":1.43277602,"remaining_time":0.07382337011},
{"learn":[3.108691641],"iteration":951,"passed_time":1.434142215,"remaining_time":0.07230969151},
{"learn":[3.107898017],"iteration":952,"passed_time":1.435381887,"remaining_time":0.07079008255},
{"learn":[3.105551729],"iteration":953,"passed_time":1.43669702,"remaining_time":0.06927469907},
{"learn":[3.104824945],"iteration":954,"passed_time":1.437899865,"remaining_time":0.06775444389},
{"learn":[3.103186704],"iteration":955,"passed_time":1.439188663,"remaining_time":0.06623880875},
{"learn":[3.102330655],"iteration":956,"passed_time":1.440506493,"remaining_time":0.06472495214},
{"learn":[3.102291298],"iteration":957,"passed_time":1.441670972,"remaining_time":0.06320478167},
{"learn":[3.100363529],"iteration":958,"passed_time":1.442972352,"remaining_time":0.06169120586},
{"learn":[3.097871596],"iteration":959,"passed_time":1.444310106,"remaining_time":0.06017958774},
{"learn":[3.097372213],"iteration":960,"passed_time":1.445624854,"remaining_time":0.05866739781},
{"learn":[3.095981813],"iteration":961,"passed_time":1.446991079,"remaining_time":0.05715765175},
{"learn":[3.095347452],"iteration":962,"passed_time":1.448171994,"remaining_time":0.05564108389},
{"learn":[3.094728409],"iteration":963,"passed_time":1.449497884,"remaining_time":0.05413062639},
{"learn":[3.094118537],"iteration":964,"passed_time":1.450786141,"remaining_time":0.05261918647},
{"learn":[3.093793695],"iteration":965,"passed_time":1.452106708,"remaining_time":0.05110934583},
{"learn":[3.092581602],"iteration":966,"passed_time":1.453342505,"remaining_time":0.04959700378},
{"learn":[3.091694202],"iteration":967,"passed_time":1.454761165,"remaining_time":0.04809127818},
{"learn":[3.090298312],"iteration":968,"passed_time":1.456216998,"remaining_time":0.04658692149},
{"learn":[3.090020107],"iteration":969,"passed_time":1.457436333,"remaining_time":0.04507535051},
{"learn":[3.088949869],"iteration":970,"passed_time":1.45872879,"remaining_time":0.04356656531},
{"learn":[3.086700204],"iteration":971,"passed_time":1.460005819,"remaining_time":0.0420577808},
{"learn":[3.086584317],"iteration":972,"passed_time":1.461277099,"remaining_time":0.04054931312},
{"learn":[3.084850742],"iteration":973,"passed_time":1.462530273,"remaining_time":0.03904084919},
{"learn":[3.084239948],"iteration":974,"passed_time":1.463841662,"remaining_time":0.03753440159},
{"learn":[3.082561673],"iteration":975,"passed_time":1.465170049,"remaining_time":0.03602877169},
{"learn":[3.07991814],"iteration":976,"passed_time":1.46652872,"remaining_time":0.03452421756},
{"learn":[3.079350277],"iteration":977,"passed_time":1.467974558,"remaining_time":0.03302192257},
{"learn":[3.077637462],"iteration":978,"passed_time":1.46946851,"remaining_time":0.03152077498},
{"learn":[3.076733301],"iteration":979,"passed_time":1.470774831,"remaining_time":0.03001581288},
{"learn":[3.07594065],"iteration":980,"passed_time":1.472171647,"remaining_time":0.02851300845},
{"learn":[3.072594655],"iteration":981,"passed_time":1.473474906,"remaining_time":0.02700870501},
{"learn":[3.071977674],"iteration":982,"passed_time":1.4748244,"remaining_time":0.02550561017},
{"learn":[3.069532634],"iteration":983,"passed_time":1.476223487,"remaining_time":0.02400363393},
{"learn":[3.068870784],"iteration":984,"passed_time":1.477460807,"remaining_time":0.02249940315},
{"learn":[3.068801463],"iteration":985,"passed_time":1.478702348,"remaining_time":0.02099577371},
{"learn":[3.067433249],"iteration":986,"passed_time":1.480068829,"remaining_time":0.01949432095},
{"learn":[3.065611456],"iteration":987,"passed_time":1.481437565,"remaining_time":0.01799316881},
{"learn":[3.063039162],"iteration":988,"passed_time":1.482788979,"remaining_time":0.01649209178},
{"learn":[3.06177873],"iteration":989,"passed_time":1.484076985,"remaining_time":0.01499067662},
{"learn":[3.061689148],"iteration":990,"passed_time":1.485382214,"remaining_time":0.01348984856},
{"learn":[3.058984039],"iteration":991,"passed_time":1.48661816,"remaining_time":0.01198885613},
{"learn":[3.057492984],"iteration":992,"passed_time":1.488026545,"remaining_time":0.01048961311},
{"learn":[3.057290731],"iteration":993,"passed_time":1.489403773,"remaining_time":0.008990364828},
{"learn":[3.056068348],"iteration":994,"passed_time":1.490690606,"remaining_time":0.00749090757},
{"learn":[3.054987307],"iteration":995,"passed_time":1.491875787,"remaining_time":0.005991469026},
{"learn":[3.054200234],"iteration":996,"passed_time":1.49323119,"remaining_time":0.00449317309},
{"learn":[3.052732869],"iteration":997,"passed_time":1.494525993,"remaining_time":0.00299504207},
{"learn":[3.051787862],"iteration":998,"passed_time":1.495863452,"remaining_time":0.001497360813},
{"learn":[3.051366222],"iteration":999,"passed_time":1.497233482,"remaining_time":0}
]}